{
"type": "FeatureCollection",
"crs": { "type": "name", "properties": { "name": "urn:ogc:def:crs:OGC:1.3:CRS84" } },
"features": [
{ "type": "Feature", "properties": { "CUT_REG": "08", "CUT_PROV": "083", "CUT_COM": "08309", "REGION": "Biobío", "PROVINCIA": "Bio-Bio", "COMUNA": "Quilleco", "SUPERFICIE": 1118.68, "C_COM_Tx": "08309", "Número_ma": "428-1-761-NC", "N°": 4136, "Código_de": "ND-0802-627", "N°__Solic": 1, "Región": "Bio Bio", "Nombre_Sol": "SUR INVERSIONES S. A.", "Unidad_de": "DGA Concepción", "Fecha_de_R": "29/06/2011", "N°_Resolu": "137", "Fecha_Toma": "25-07-2011", "Artículo": "", "Tipo_Derec": "No Consuntivo", "Naturaleza": "Superficial y Corriente", "Clasificac": "Rio/Estero", "Uso_del_Ag": "", "Cuenca": "", "SubCuenca": "Rio Duqueco", "SubSubCuen": "Rio Duqueco Entre Estero Quilleco y Rio Coreo", "Fuente": "", "Enero": "0,0010", "Febrero": "0,0010", "Marzo": "0,0040", "Abril": "0,0200", "Mayo": "0,0800", "Junio": "0,0710", "Julio": "", "Agosto": "", "Septiembre": "", "Octubre": "0,0170", "Noviembre": "", "Diciembre": "", "Ejercicio": "Permanente y Continuo", "Caudal__An": 0.0282, "Unidad_d_1": "m3/s", "¿Caudal_P": "SI", "Caudal_Eco": "13,0833", "¿Caudal_E": "SI", "Acciones_e": 0, "Acciones_1": 0, "UTM__Norte": 5846905, "UTM__Este": 760999, "Huso": "18", "Datum": "1956", "Latitud__C": "", "Longitud__": "", "Datum1": "", "UTM__Nor_1": 5846776, "UTM__Est_1": 758142.0, "Latitud__R": "", "Longitud_1": "", "Referencia": "", "Referenc_1": "", "Distancia": 2681.0, "Unidad_Dis": "mts", "Desnivel__": 20.0, "C_B_R_": "C.B.R. Los Ángeles", "Fojas": "354", "N°_CBR": 251, "Año": 2011, "Código_Ex": "(0-0-0)", "¿Posee__m": "", "N°_Certif": "3574/2017", "Tiene_Renu": "NO", "Tiene_Tran": "NO", "DAA_subter": "", "Titular_ca": "", "DAA_con_ca": "", "Link_al_Ve": "", "DAA_que_pe": "", "Verificado": "", "DAA_catast": "", "Catastro_n": "", "Link_al__1": "", "DAA_no_vig": "", "Link_a_la": "", "Inscripci": "PDF", "CPA": "3574-2017", "Caudal_Lt_": 28.2, "Caudal_suj": 0, "Verificaci": "Con obras", "Caudal_a_r": 0, "ACIONES_CO": 0, "Caudal_a_1": 0.0282, "ACCIONES_N": 20.465006, "URL_de_Ins": "https://drive.google.com/file/d/17LJnk8Sg2uAqzDMiuO6ViTVYwqx0nE5W/view?usp=sharing", "URL_de_CPA": "https://drive.google.com/file/d/1Wf2p8TglJdH0-5nKs1ldb4hhyutQ-Mtx/view?usp=sharing", "N°_de_Sub": 400, "Nuevo_SUBS": 428, "N°_de_cla": 1, "Nuevo_núm": 761, "Nuevo_nú_": "#NAME?", "Nuevo_nú1": "428-1-761-NC", "N°_de_Reg": "", "N°_de_Usu": "", "Rut": "96.954.810-0", "Giro_eléc": "NO", "Correlativo": 1, "Consuntivo": "No Consuntivos" }, "geometry": { "type": "Point", "coordinates": [ -72.050652146034267, -37.490599372397647 ] } },
{ "type": "Feature", "properties": { "CUT_REG": "08", "CUT_PROV": "083", "CUT_COM": "08309", "REGION": "Biobío", "PROVINCIA": "Bio-Bio", "COMUNA": "Quilleco", "SUPERFICIE": 1118.68, "C_COM_Tx": "08309", "Número_ma": "428-1-769-NC", "N°": 6756, "Código_de": "ND-0802-463", "N°__Solic": 1, "Región": "Bio Bio", "Nombre_Sol": "PISCICULTURA PICHI-COREO LIMITADA", "Unidad_de": "Dirección General de Aguas", "Fecha_de_R": "13/07/2004", "N°_Resolu": "268", "Fecha_Toma": "19-07-2004", "Artículo": "", "Tipo_Derec": "No Consuntivo", "Naturaleza": "Superficial y Corriente", "Clasificac": "Rio/Estero", "Uso_del_Ag": "Piscicultura", "Cuenca": "", "SubCuenca": "Rio Duqueco", "SubSubCuen": "Rio Duqueco Entre Estero Quilleco y Rio Coreo", "Fuente": "", "Enero": "197", "Febrero": "197", "Marzo": "197", "Abril": "197", "Mayo": "197", "Junio": "197", "Julio": "", "Agosto": "", "Septiembre": "", "Octubre": "197", "Noviembre": "", "Diciembre": "", "Ejercicio": "Permanente y Continuo", "Caudal__An": 197.0, "Unidad_d_1": "Lt/s", "¿Caudal_P": "SI", "Caudal_Eco": "21", "¿Caudal_E": "", "Acciones_e": 0, "Acciones_1": 0, "UTM__Norte": 5846900, "UTM__Este": 761050, "Huso": "18", "Datum": "1956", "Latitud__C": "", "Longitud__": "", "Datum1": "", "UTM__Nor_1": 5846900, "UTM__Est_1": 761000.0, "Latitud__R": "", "Longitud_1": "", "Referencia": "DESDE UN PUNTO DEFINIDO POR COORDENADAS UTM.", "Referenc_1": "", "Distancia": 50.0, "Unidad_Dis": "mts", "Desnivel__": 0.7, "C_B_R_": "C.B.R. Los Ángeles", "Fojas": "4", "N°_CBR": 3, "Año": 2005, "Código_Ex": "(0-0-0)", "¿Posee__m": "", "N°_Certif": "1042/2005", "Tiene_Renu": "NO", "Tiene_Tran": "NO", "DAA_subter": "", "Titular_ca": "", "DAA_con_ca": "", "Link_al_Ve": "", "DAA_que_pe": "", "Verificado": "", "DAA_catast": "", "Catastro_n": "", "Link_al__1": "", "DAA_no_vig": "", "Link_a_la": "", "Inscripci": "PDF", "CPA": "1042-2005", "Caudal_Lt_": 197.0, "Caudal_suj": 0, "Verificaci": "Con obras", "Caudal_a_r": 0, "ACIONES_CO": 0, "Caudal_a_1": 0.197, "ACCIONES_N": 142.964761, "URL_de_Ins": "https://drive.google.com/file/d/1Ezt_FWDxk63grkTRttz_vgjE6IZ4tePR/view?usp=sharing", "URL_de_CPA": "https://drive.google.com/file/d/1GoTQUwTXcRmIZjwY-iNldSrCXsjrS5vq/view?usp=sharing", "N°_de_Sub": 400, "Nuevo_SUBS": 428, "N°_de_cla": 1, "Nuevo_núm": 769, "Nuevo_nú_": "#NAME?", "Nuevo_nú1": "428-1-769-NC", "N°_de_Reg": "", "N°_de_Usu": "", "Rut": "78.981.490-2", "Giro_eléc": "NO", "Correlativo": 1, "Consuntivo": "No Consuntivos" }, "geometry": { "type": "Point", "coordinates": [ -72.050074248309429, -37.490629983433713 ] } },
{ "type": "Feature", "properties": { "CUT_REG": "08", "CUT_PROV": "083", "CUT_COM": "08309", "REGION": "Biobío", "PROVINCIA": "Bio-Bio", "COMUNA": "Quilleco", "SUPERFICIE": 1118.68, "C_COM_Tx": "08309", "Número_ma": "425-1-721-NC", "N°": 4199, "Código_de": "ND-0802-3922", "N°__Solic": 1, "Región": "Bio Bio", "Nombre_Sol": "SOCIEDAD ELECTRICA DE MAVA  LIMITADA", "Unidad_de": "DGA Concepción", "Fecha_de_R": "01/04/2011", "N°_Resolu": "42", "Fecha_Toma": "14-06-2011", "Artículo": "", "Tipo_Derec": "No Consuntivo", "Naturaleza": "Superficial y Corriente", "Clasificac": "Rio/Estero", "Uso_del_Ag": "", "Cuenca": "", "SubCuenca": "Rio Duqueco", "SubSubCuen": "Rio Duqueco Hasta Bajo Estero Paulin", "Fuente": "", "Enero": "107,9000", "Febrero": "86", "Marzo": "66,3000", "Abril": "50,2000", "Mayo": "134,7000", "Junio": "428", "Julio": "", "Agosto": "", "Septiembre": "", "Octubre": "367,3000", "Noviembre": "", "Diciembre": "", "Ejercicio": "Permanente y Continuo", "Caudal__An": 267.425, "Unidad_d_1": "Lt/s", "¿Caudal_P": "SI", "Caudal_Eco": "91,3333", "¿Caudal_E": "SI", "Acciones_e": 0, "Acciones_1": 0, "UTM__Norte": 5845097, "UTM__Este": 270392, "Huso": "19", "Datum": "1956", "Latitud__C": "", "Longitud__": "", "Datum1": "", "UTM__Nor_1": 5842405, "UTM__Est_1": 270645.0, "Latitud__R": "", "Longitud_1": "", "Referencia": "", "Referenc_1": "", "Distancia": 2715.0, "Unidad_Dis": "mts", "Desnivel__": 248.0, "C_B_R_": "C.B.R. Los Ángeles", "Fojas": "307", "N°_CBR": 219, "Año": 2011, "Código_Ex": "(0-0-0)", "¿Posee__m": "", "N°_Certif": "4738/2012", "Tiene_Renu": "NO", "Tiene_Tran": "NO", "DAA_subter": "", "Titular_ca": "", "DAA_con_ca": "", "Link_al_Ve": "", "DAA_que_pe": "", "Verificado": "", "DAA_catast": "", "Catastro_n": "", "Link_al__1": "", "DAA_no_vig": "", "Link_a_la": "", "Inscripci": "PDF", "CPA": "4738-2012", "Caudal_Lt_": 267.425, "Caudal_suj": 0, "Verificaci": "Con obras", "Caudal_a_r": 0, "ACIONES_CO": 0, "Caudal_a_1": 0.267425, "ACCIONES_N": 194.072848, "URL_de_Ins": "https://drive.google.com/file/d/1S2XPYt1-TSM9up5Xu93WaG6MYlkDI0hI/view?usp=sharing", "URL_de_CPA": "https://drive.google.com/file/d/1Pkh0lisIiGXLIlhlkmfJk2QWjZwd_tx7/view?usp=sharing", "N°_de_Sub": 400, "Nuevo_SUBS": 425, "N°_de_cla": 1, "Nuevo_núm": 721, "Nuevo_nú_": "#NAME?", "Nuevo_nú1": "425-1-721-NC", "N°_de_Reg": "", "N°_de_Usu": "", "Rut": "76.045.155-K", "Giro_eléc": "NO", "Correlativo": 4, "Consuntivo": "No Consuntivos" }, "geometry": { "type": "Point", "coordinates": [ -71.600198346968853, -37.515223922346557 ] } },
{ "type": "Feature", "properties": { "CUT_REG": "08", "CUT_PROV": "083", "CUT_COM": "08309", "REGION": "Biobío", "PROVINCIA": "Bio-Bio", "COMUNA": "Quilleco", "SUPERFICIE": 1118.68, "C_COM_Tx": "08309", "Número_ma": "426-1-733-NC", "N°": 5087, "Código_de": "ND-0802-354", "N°__Solic": 1, "Región": "Bio Bio", "Nombre_Sol": "HACIENDA SAN LORENZO S.A.", "Unidad_de": "DGA Concepción", "Fecha_de_R": "27/10/2009", "N°_Resolu": "247", "Fecha_Toma": "19-01-2010", "Artículo": "", "Tipo_Derec": "No Consuntivo", "Naturaleza": "Superficial y Corriente", "Clasificac": "Rio/Estero", "Uso_del_Ag": "Energia Hidroeléctrica", "Cuenca": "", "SubCuenca": "Rio Duqueco", "SubSubCuen": "Rio Duqueco Entre Estero Paulin y Bajo Estero Cañicura", "Fuente": "", "Enero": "", "Febrero": "", "Marzo": "", "Abril": "", "Mayo": "", "Junio": "0,4810", "Julio": "", "Agosto": "", "Septiembre": "", "Octubre": "", "Noviembre": "", "Diciembre": "", "Ejercicio": "Eventual y Discontinuo", "Caudal__An": 0.2049, "Unidad_d_1": "m3/s", "¿Caudal_P": "SI", "Caudal_Eco": "908,5000", "¿Caudal_E": "SI", "Acciones_e": 0, "Acciones_1": 0, "UTM__Norte": 5847600, "UTM__Este": 255800, "Huso": "19", "Datum": "1956", "Latitud__C": "", "Longitud__": "", "Datum1": "", "UTM__Nor_1": 5841500, "UTM__Est_1": 245350.0, "Latitud__R": "", "Longitud_1": "", "Referencia": "", "Referenc_1": "", "Distancia": 16000.0, "Unidad_Dis": "", "Desnivel__": 200.0, "C_B_R_": "C.B.R. Los Ángeles", "Fojas": "108", "N°_CBR": 89, "Año": 2010, "Código_Ex": "(0-0-0)", "¿Posee__m": "", "N°_Certif": "2086/2010", "Tiene_Renu": "NO", "Tiene_Tran": "NO", "DAA_subter": "", "Titular_ca": "", "DAA_con_ca": "", "Link_al_Ve": "", "DAA_que_pe": "", "Verificado": "", "DAA_catast": "", "Catastro_n": "", "Link_al__1": "", "DAA_no_vig": "", "Link_a_la": "", "Inscripci": "PDF", "CPA": "", "Caudal_Lt_": 204.9, "Caudal_suj": 0, "Verificaci": "Con obras", "Caudal_a_r": 0, "ACIONES_CO": 0, "Caudal_a_1": 0.2049, "ACCIONES_N": 148.697865, "URL_de_Ins": "https://drive.google.com/file/d/1A7yay7CYNZSAVZZYfVWAGUM2PNpcrH0H/view?usp=sharing", "URL_de_CPA": "", "N°_de_Sub": 400, "Nuevo_SUBS": 426, "N°_de_cla": 1, "Nuevo_núm": 733, "Nuevo_nú_": "#NAME?", "Nuevo_nú1": "426-1-733-NC", "N°_de_Reg": "", "N°_de_Usu": "", "Rut": "96.693.850-1", "Giro_eléc": "NO", "Correlativo": 4, "Consuntivo": "No Consuntivos" }, "geometry": { "type": "Point", "coordinates": [ -71.76429523353633, -37.488941601806133 ] } },
{ "type": "Feature", "properties": { "CUT_REG": "08", "CUT_PROV": "083", "CUT_COM": "08309", "REGION": "Biobío", "PROVINCIA": "Bio-Bio", "COMUNA": "Tucapel", "SUPERFICIE": 1118.68, "C_COM_Tx": "08309", "Número_ma": "427-1-746-NC", "N°": 5747, "Código_de": "ND-0802-706", "N°__Solic": 1, "Región": "Bio Bio", "Nombre_Sol": "JUAN FRANCISCO GALLEGOS DOMINGUEZ Y OTROS", "Unidad_de": "DGA Concepción", "Fecha_de_R": "02/04/2008", "N°_Resolu": "61", "Fecha_Toma": "10-04-2008", "Artículo": "", "Tipo_Derec": "No Consuntivo", "Naturaleza": "Superficial y Corriente", "Clasificac": "Rio/Estero", "Uso_del_Ag": "", "Cuenca": "", "SubCuenca": "Rio Duqueco", "SubSubCuen": "Rio Duqueco Entre Estero Cañicura y Bajo Rio Quilleco", "Fuente": "", "Enero": "4", "Febrero": "", "Marzo": "", "Abril": "", "Mayo": "9", "Junio": "146", "Julio": "", "Agosto": "", "Septiembre": "", "Octubre": "122", "Noviembre": "", "Diciembre": "", "Ejercicio": "Permanente y Discontinuo", "Caudal__An": 78.6667, "Unidad_d_1": "Lt/s", "¿Caudal_P": "SI", "Caudal_Eco": "10,2000", "¿Caudal_E": "", "Acciones_e": 0, "Acciones_1": 0, "UTM__Norte": 5842587, "UTM__Este": 240137, "Huso": "19", "Datum": "1956", "Latitud__C": "", "Longitud__": "", "Datum1": "", "UTM__Nor_1": 5842583, "UTM__Est_1": 240012.0, "Latitud__R": "", "Longitud_1": "", "Referencia": "", "Referenc_1": "", "Distancia": 125.0, "Unidad_Dis": "", "Desnivel__": 7.0, "C_B_R_": "C.B.R. Los Ángeles", "Fojas": "110", "N°_CBR": 89, "Año": 2009, "Código_Ex": "(0-0-0)", "¿Posee__m": "", "N°_Certif": "1603/2009", "Tiene_Renu": "NO", "Tiene_Tran": "NO", "DAA_subter": "", "Titular_ca": "", "DAA_con_ca": "", "Link_al_Ve": "", "DAA_que_pe": "", "Verificado": "", "DAA_catast": "", "Catastro_n": "", "Link_al__1": "", "DAA_no_vig": "", "Link_a_la": "", "Inscripci": "PDF", "CPA": "", "Caudal_Lt_": 78.6667, "Caudal_suj": 0, "Verificaci": "Con obras", "Caudal_a_r": 0, "ACIONES_CO": 0, "Caudal_a_1": 0.078667, "ACCIONES_N": 57.089167, "URL_de_Ins": "https://drive.google.com/file/d/121v2jjCMaRdWgx6eU3rOmvsgE8PhfU_l/view?usp=sharing", "URL_de_CPA": "", "N°_de_Sub": 400, "Nuevo_SUBS": 427, "N°_de_cla": 1, "Nuevo_núm": 746, "Nuevo_nú_": "#NAME?", "Nuevo_nú1": "427-1-746-NC", "N°_de_Reg": "", "N°_de_Usu": "", "Rut": "", "Giro_eléc": "", "Correlativo": 4, "Consuntivo": "No Consuntivos" }, "geometry": { "type": "Point", "coordinates": [ -71.943012924068412, -37.529789937278657 ] } },
{ "type": "Feature", "properties": { "CUT_REG": "08", "CUT_PROV": "083", "CUT_COM": "08309", "REGION": "Biobío", "PROVINCIA": "Bio-Bio", "COMUNA": "Quilleco", "SUPERFICIE": 1118.68, "C_COM_Tx": "08309", "Número_ma": "426-1-738-NC", "N°": 6907, "Código_de": "ND-0802-519", "N°__Solic": 1, "Región": "Bio Bio", "Nombre_Sol": "JUAN CARLOS CARRIO BIONDI", "Unidad_de": "Dirección General de Aguas", "Fecha_de_R": "23/09/2003", "N°_Resolu": "497", "Fecha_Toma": "30-09-2003", "Artículo": "", "Tipo_Derec": "No Consuntivo", "Naturaleza": "Superficial y Corriente", "Clasificac": "Rio/Estero", "Uso_del_Ag": "", "Cuenca": "", "SubCuenca": "Rio Duqueco", "SubSubCuen": "Rio Duqueco Entre Estero Paulin y Bajo Estero Cañicura", "Fuente": "", "Enero": "26", "Febrero": "16", "Marzo": "16", "Abril": "", "Mayo": "6", "Junio": "36", "Julio": "", "Agosto": "", "Septiembre": "", "Octubre": "36", "Noviembre": "", "Diciembre": "", "Ejercicio": "Eventual y Discontinuo", "Caudal__An": 24.6667, "Unidad_d_1": "Lt/s", "¿Caudal_P": "SI", "Caudal_Eco": "86", "¿Caudal_E": "", "Acciones_e": 0, "Acciones_1": 0, "UTM__Norte": 5844515, "UTM__Este": 260661, "Huso": "19", "Datum": "1956", "Latitud__C": "", "Longitud__": "", "Datum1": "", "UTM__Nor_1": 5843990, "UTM__Est_1": 260034.7, "Latitud__R": "", "Longitud_1": "", "Referencia": "", "Referenc_1": "", "Distancia": 835.0, "Unidad_Dis": "mts", "Desnivel__": 55.0, "C_B_R_": "C.B.R. Los Ángeles", "Fojas": "26", "N°_CBR": 18, "Año": 2004, "Código_Ex": "(0-0-0)", "¿Posee__m": "", "N°_Certif": "347/2008", "Tiene_Renu": "NO", "Tiene_Tran": "NO", "DAA_subter": "", "Titular_ca": "", "DAA_con_ca": "", "Link_al_Ve": "", "DAA_que_pe": "", "Verificado": "", "DAA_catast": "", "Catastro_n": "", "Link_al__1": "", "DAA_no_vig": "", "Link_a_la": "", "Inscripci": "PDF", "CPA": "347-2008", "Caudal_Lt_": 24.6667, "Caudal_suj": 0, "Verificaci": "Con obras", "Caudal_a_r": 0, "ACIONES_CO": 0, "Caudal_a_1": 0.024667, "ACCIONES_N": 17.900857, "URL_de_Ins": "https://drive.google.com/file/d/1R0cjxacjsD-VFS3OXZouquq_tI_tZMaJ/view?usp=sharing", "URL_de_CPA": "https://drive.google.com/file/d/1223DDRGsT3-3Yq8OctG_OTYSEh-mYttX/view?usp=sharing", "N°_de_Sub": 400, "Nuevo_SUBS": 426, "N°_de_cla": 1, "Nuevo_núm": 738, "Nuevo_nú_": "#NAME?", "Nuevo_nú1": "426-1-738-NC", "N°_de_Reg": "", "N°_de_Usu": "", "Rut": "6.340.624-4", "Giro_eléc": "NO", "Correlativo": 4, "Consuntivo": "No Consuntivos" }, "geometry": { "type": "Point", "coordinates": [ -71.710377484366745, -37.517989707266182 ] } },
{ "type": "Feature", "properties": { "CUT_REG": "08", "CUT_PROV": "083", "CUT_COM": "08309", "REGION": "Biobío", "PROVINCIA": "Bio-Bio", "COMUNA": "Quilleco", "SUPERFICIE": 1118.68, "C_COM_Tx": "08309", "Número_ma": "426-1-740-NC", "N°": 7517, "Código_de": "ND-0802-224", "N°__Solic": 1, "Región": "Bio Bio", "Nombre_Sol": "HACIENDA SAN LORENZO S.A.", "Unidad_de": "Dirección General de Aguas", "Fecha_de_R": "30/06/2000", "N°_Resolu": "356", "Fecha_Toma": "06-07-2000", "Artículo": "", "Tipo_Derec": "No Consuntivo", "Naturaleza": "Superficial y Corriente", "Clasificac": "Rio/Estero", "Uso_del_Ag": "Otros Usos", "Cuenca": "", "SubCuenca": "Rio Duqueco", "SubSubCuen": "Rio Duqueco Entre Estero Paulin y Bajo Estero Cañicura", "Fuente": "", "Enero": "0,3700", "Febrero": "0,2700", "Marzo": "0,1400", "Abril": "", "Mayo": "0,0800", "Junio": "0,4100", "Julio": "", "Agosto": "", "Septiembre": "", "Octubre": "0,5100", "Noviembre": "", "Diciembre": "", "Ejercicio": "Permanente y Discontinuo", "Caudal__An": 0.3592, "Unidad_d_1": "m3/s", "¿Caudal_P": "SI", "Caudal_Eco": "82,5000", "¿Caudal_E": "SI", "Acciones_e": 0, "Acciones_1": 0, "UTM__Norte": 5843900, "UTM__Este": 259950, "Huso": "19", "Datum": "1956", "Latitud__C": "", "Longitud__": "", "Datum1": "", "UTM__Nor_1": 5845250, "UTM__Est_1": 251000.0, "Latitud__R": "", "Longitud_1": "", "Referencia": "", "Referenc_1": "", "Distancia": 9.0, "Unidad_Dis": "Km", "Desnivel__": 100.0, "C_B_R_": "C.B.R. Los Ángeles", "Fojas": "135", "N°_CBR": 119, "Año": 2008, "Código_Ex": "(0-0-0)", "¿Posee__m": "", "N°_Certif": "2108/2010", "Tiene_Renu": "NO", "Tiene_Tran": "NO", "DAA_subter": "", "Titular_ca": "", "DAA_con_ca": "", "Link_al_Ve": "", "DAA_que_pe": "", "Verificado": "", "DAA_catast": "", "Catastro_n": "", "Link_al__1": "", "DAA_no_vig": "", "Link_a_la": "", "Inscripci": "PDF", "CPA": "", "Caudal_Lt_": 359.2, "Caudal_suj": 0, "Verificaci": "Con obras", "Caudal_a_r": 0, "ACIONES_CO": 0, "Caudal_a_1": 0.3592, "ACCIONES_N": 260.674832, "URL_de_Ins": "https://drive.google.com/file/d/16rDfvJabKvIXvyTmvFk2cqI6H1ZfBh4s/view?usp=sharing", "URL_de_CPA": "", "N°_de_Sub": 400, "Nuevo_SUBS": 426, "N°_de_cla": 1, "Nuevo_núm": 740, "Nuevo_nú_": "#NAME?", "Nuevo_nú1": "426-1-740-NC", "N°_de_Reg": "", "N°_de_Usu": "", "Rut": "96.693.850-1", "Giro_eléc": "NO", "Correlativo": 4, "Consuntivo": "No Consuntivos" }, "geometry": { "type": "Point", "coordinates": [ -71.718614968234419, -37.523341819949145 ] } },
{ "type": "Feature", "properties": { "CUT_REG": "08", "CUT_PROV": "083", "CUT_COM": "08309", "REGION": "Biobío", "PROVINCIA": "Bio-Bio", "COMUNA": "Santa Bárbara", "SUPERFICIE": 1118.68, "C_COM_Tx": "08309", "Número_ma": "427-1-755-NC", "N°": 7879, "Código_de": "VT-0802-8", "N°__Solic": 1, "Región": "Bio Bio", "Nombre_Sol": "DUQUECO SPA", "Unidad_de": "DGA Concepción", "Fecha_de_R": "25/11/1996", "N°_Resolu": "116", "Fecha_Toma": "31-12-1996", "Artículo": "", "Tipo_Derec": "No Consuntivo", "Naturaleza": "Superficial y Corriente", "Clasificac": "Rio/Estero", "Uso_del_Ag": "", "Cuenca": "", "SubCuenca": "Rio Duqueco", "SubSubCuen": "Rio Duqueco Entre Estero Cañicura y Bajo Rio Quilleco", "Fuente": "", "Enero": "25", "Febrero": "25", "Marzo": "25", "Abril": "25", "Mayo": "25", "Junio": "25", "Julio": "", "Agosto": "", "Septiembre": "", "Octubre": "25", "Noviembre": "", "Diciembre": "", "Ejercicio": "Permanente y Continuo", "Caudal__An": 25.0, "Unidad_d_1": "m3/s", "¿Caudal_P": "SI", "Caudal_Eco": "1500", "¿Caudal_E": "", "Acciones_e": 0, "Acciones_1": 0, "UTM__Norte": 5842691, "UTM__Este": 270874, "Huso": "19", "Datum": "1956", "Latitud__C": "", "Longitud__": "", "Datum1": "", "UTM__Nor_1": 5845130, "UTM__Est_1": 250070.0, "Latitud__R": "", "Longitud_1": "", "Referencia": "", "Referenc_1": "", "Distancia": 5.0, "Unidad_Dis": "Km", "Desnivel__": 500.0, "C_B_R_": "C.B.R. Santa Bárbara", "Fojas": "88 VTA.", "N°_CBR": 65, "Año": 1997, "Código_Ex": "(0-0-0)", "¿Posee__m": "", "N°_Certif": "3718/2015", "Tiene_Renu": "NO", "Tiene_Tran": "NO", "DAA_subter": "", "Titular_ca": "", "DAA_con_ca": "", "Link_al_Ve": "", "DAA_que_pe": "", "Verificado": "", "DAA_catast": "", "Catastro_n": "", "Link_al__1": "", "DAA_no_vig": "", "Link_a_la": "", "Inscripci": "PDF", "CPA": "", "Caudal_Lt_": 25000.0, "Caudal_suj": 0, "Verificaci": "Con obras", "Caudal_a_r": 0, "ACIONES_CO": 0, "Caudal_a_1": 25.0, "ACCIONES_N": 18142.73611, "URL_de_Ins": "https://drive.google.com/file/d/1GG-8B94dsCZYvSCq3a_ZVHPU9siT1ojh/view?usp=sharing", "URL_de_CPA": "", "N°_de_Sub": 400, "Nuevo_SUBS": 427, "N°_de_cla": 1, "Nuevo_núm": 755, "Nuevo_nú_": "#NAME?", "Nuevo_nú1": "427-1-755-NC", "N°_de_Reg": "", "N°_de_Usu": "", "Rut": "76.254.033-9", "Giro_eléc": "SÍ", "Correlativo": 4, "Consuntivo": "No Consuntivos" }, "geometry": { "type": "Point", "coordinates": [ -71.595500864385045, -37.537007496554097 ] } }
]
}
