{
"type": "FeatureCollection",
"crs": { "type": "name", "properties": { "name": "urn:ogc:def:crs:EPSG::4979" } },
"features": [
{ "type": "Feature", "properties": { "CODATRAC": "R040003", "JERARQUIA": "REGIONAL", "CATEGORIA": "REALIZACIONES TÉCNICAS Y CIENTÍFICAS CONTEMPORÁNEAS Y CULTURALES HISTÓRICAS", "TIPO": "OBRAS DE ARTE Y TÉCNICA", "SUBTIPO": "REALIZACIÓN URBANA", "NOMBRE": "ALAMEDA DE OVALLE", "REGION": "REGIÓN DE COQUIMBO", "PROVINCIA": "LIMARI", "COMUNA": "OVALLE", "LOCALIDAD": "OVALLE", "DIRECCION": "ARIZTIA ORIENTE Y PONIENTE S/N, OVALLE", "TELEFONO": "(53) 661238", "PROPIEDAD": "PÚBLICA", "ADMINISTRA": "PÚBLICA", "DISTCR": "88", "CR": "LA SERENA", "DISTCC": "0", "CC": "OVALLE", "LOC_URBANA": "OVALLE", "ESTACIONAL": "TODO EL AÑO", "USO_TUR": "ACTUAL", "DEMANDA": "LOCAL, REGIONAL", "SERVICIOS": "AGUA POTABLE, ELECTRICIDAD", "COD_REG": 4, "COD_PROV": 43, "COD_COM": 4301, "DESCRIPCIO": "Es el principal paseo público que se extiende por cuatro cuadras. Cuenta con hermosas palmeras y jardines. La tercera cuadra está dotada de un hermoso espejo de agua y un monumento en honor a Pedro Enrique Alfonso.", "ESTADO_1": "BUENA", "POINT_X": -71.197466387000006, "POINT_Y": -30.602341165799999 }, "geometry": { "type": "Point", "coordinates": [ -71.197466386999963, -30.602341165827252, 0.0 ] } },
{ "type": "Feature", "properties": { "CODATRAC": "R040024", "JERARQUIA": "LOCAL", "CATEGORIA": "FOLKLORE", "TIPO": "ARQUITECTURA POPULAR ESPONTÁNEA", "SUBTIPO": "PUEBLO O ALDEA TRADICIONAL", "NOMBRE": "BARRAZA", "REGION": "REGIÓN DE COQUIMBO", "PROVINCIA": "LIMARI", "COMUNA": "OVALLE", "LOCALIDAD": "BARRAZA", "DIRECCION": "A 30 KM AL OESTE DE OVALLE", "TELEFONO": "(53) 661238", "PROPIEDAD": "PÚBLICA", "ADMINISTRA": "PÚBLICA", "DISTCR": "118", "CR": "LA SERENA", "DISTCC": "30", "CC": "OVALLE", "LOC_URBANA": "OVALLE", "ESTACIONAL": "TODO EL AÑO", "USO_TUR": "ACTUAL", "DEMANDA": "LOCAL", "SERVICIOS": "AGUA POTABLE, ELECTRICIDAD", "COD_REG": 4, "COD_PROV": 43, "COD_COM": 4301, "DESCRIPCIO": "Barraza es pequeño poblado ubicado en la ribera sur del río Limarí. Su historia está íntimamente ligada a la de su iglesia parroquial, diseñada por Joaquín Toesca, Monumento Nacional chileno.", "ESTADO_1": "BUENA", "POINT_X": -71.480726934000003, "POINT_Y": -30.6551883978 }, "geometry": { "type": "Point", "coordinates": [ -71.480726933999961, -30.655188397828056, 0.0 ] } },
{ "type": "Feature", "properties": { "CODATRAC": "R040101", "JERARQUIA": "REGIONAL", "CATEGORIA": "REALIZACIONES TÉCNICAS Y CIENTÍFICAS CONTEMPORÁNEAS Y CULTURALES HISTÓRICAS", "TIPO": "OBRAS DE ARTE Y TÉCNICA", "SUBTIPO": "OBRA DE INGENIERÍA", "NOMBRE": "EMBALSE RECOLETA", "REGION": "REGIÓN DE COQUIMBO", "PROVINCIA": "LIMARI", "COMUNA": "OVALLE", "LOCALIDAD": "RECOLETA", "DIRECCION": "A 17 KM AL NORESTE DE OVALLE", "TELEFONO": "(53) 661238", "PROPIEDAD": "PRIVADA", "ADMINISTRA": "PRIVADA", "DISTCR": "96", "CR": "LA SERENA", "DISTCC": "17", "CC": "OVALLE", "LOC_URBANA": "OVALLE", "ESTACIONAL": "TODO EL AÑO", "USO_TUR": "ACTUAL", "DEMANDA": "LOCAL, REGIONAL", "SERVICIOS": "AGUA POTABLE, ELECTRICIDAD", "COD_REG": 4, "COD_PROV": 43, "COD_COM": 4301, "DESCRIPCIO": "Embalsa las aguas de los ríos Hurtado y Higuerillas. Su construcción comenzó en 1929 y finalizó en 1934.Posee una capacidad de 100 millones de metros cúbicos destinados exclusivamente para riego, cubriendo una superficie total de 555 hectáreas.", "ESTADO_1": "BUENA", "POINT_X": -71.094282077000003, "POINT_Y": -30.490007627800001 }, "geometry": { "type": "Point", "coordinates": [ -71.094282076999946, -30.490007627825438, 0.0 ] } },
{ "type": "Feature", "properties": { "CODATRAC": "R040113", "JERARQUIA": "REGIONAL", "CATEGORIA": "FOLKLORE", "TIPO": "FERIAS Y MERCADOS", "SUBTIPO": "FERIA ARTESANAL O TRADICIONAL", "NOMBRE": "FERIA MODELO DE OVALLE", "REGION": "REGIÓN DE COQUIMBO", "PROVINCIA": "LIMARI", "COMUNA": "OVALLE", "LOCALIDAD": "OVALLE", "DIRECCION": "MAESTRANZA S/N, OVALLE", "TELEFONO": "(53) 661238", "PROPIEDAD": "PÚBLICA", "ADMINISTRA": "PÚBLICA", "DISTCR": "88", "CR": "LA SERENA", "DISTCC": "0", "CC": "OVALLE", "LOC_URBANA": "OVALLE", "ESTACIONAL": "TODO EL AÑO", "USO_TUR": "ACTUAL", "DEMANDA": "LOCAL, REGIONAL", "SERVICIOS": "AGUA POTABLE, ELECTRICIDAD", "COD_REG": 4, "COD_PROV": 43, "COD_COM": 4301, "DESCRIPCIO": "Es la mayor feria agrícola del norte del país. Es el corazón comercial del Limarí. Fue inaugurada el 21 de abril de 1986 y construida donde antiguamente estaba la maestranza de Ferrocarriles del Estado.", "ESTADO_1": "BUENA", "POINT_X": -71.197335959, "POINT_Y": -30.597950355799998 }, "geometry": { "type": "Point", "coordinates": [ -71.197335958999986, -30.597950355827166, 0.0 ] } },
{ "type": "Feature", "properties": { "CODATRAC": "R040114", "JERARQUIA": "NACIONAL", "CATEGORIA": "ACONTECIMIENTOS PROGRAMADOS", "TIPO": "EVENTOS MISCELÁNEOS", "SUBTIPO": "CARNAVAL O FIESTA COSTUMBRISTA", "NOMBRE": "FERIA NACIONAL DEL LIBRO DE OVALLE", "REGION": "REGIÓN DE COQUIMBO", "PROVINCIA": "LIMARI", "COMUNA": "OVALLE", "LOCALIDAD": "OVALLE", "DIRECCION": "", "TELEFONO": "", "PROPIEDAD": "PUBLICA", "ADMINISTRA": "PUBLICA", "DISTCR": "88", "CR": "LA SERENA", "DISTCC": "0", "CC": "OVALLE", "LOC_URBANA": "OVALLE", "ESTACIONAL": "FEBRERO", "USO_TUR": "ACTUAL", "DEMANDA": "LOCAL, REGIONAL, NACIONAL", "SERVICIOS": "SERVICIOS COMPLETOS", "COD_REG": 4, "COD_PROV": 43, "COD_COM": 4301, "DESCRIPCIO": "Durante segunde quincena de febrero. La fiesta cultural mas tradicional de Ovalle, momento en el cual la literatura entra en contacto con las demás artes. Se desarrrolla en la Plaza de Armas.", "ESTADO_1": "BUENA", "POINT_X": -71.203051404999997, "POINT_Y": -30.6030403488 }, "geometry": { "type": "Point", "coordinates": [ -71.20305140499994, -30.603040348827268, 0.0 ] } },
{ "type": "Feature", "properties": { "CODATRAC": "R040119", "JERARQUIA": "LOCAL", "CATEGORIA": "ACONTECIMIENTOS PROGRAMADOS", "TIPO": "EVENTOS MISCELÁNEOS", "SUBTIPO": "CARNAVAL O FIESTA COSTUMBRISTA", "NOMBRE": "FIESTA COSTUMBRISTA DE BARRAZA", "REGION": "REGIÓN DE COQUIMBO", "PROVINCIA": "LIMARI", "COMUNA": "OVALLE", "LOCALIDAD": "BARRAZA", "DIRECCION": "", "TELEFONO": "", "PROPIEDAD": "PÚBLICA", "ADMINISTRA": "PÚBLICA", "DISTCR": "118", "CR": "LA SERENA", "DISTCC": "30", "CC": "OVALLE", "LOC_URBANA": "OVALLE", "ESTACIONAL": "FEBRERO", "USO_TUR": "ACTUAL", "DEMANDA": "LOCAL", "SERVICIOS": "SERVICIOS COMPLETOS", "COD_REG": 4, "COD_PROV": 43, "COD_COM": 4301, "DESCRIPCIO": "Barraza les hace participe de sus costumbres y tradiciones que no se perderán con el transcurso de los años y que vivirán en aquellos que habitan en este lugar.", "ESTADO_1": "BUENA", "POINT_X": -71.481794941000004, "POINT_Y": -30.6553393698 }, "geometry": { "type": "Point", "coordinates": [ -71.481794940999976, -30.655339369828045, 0.0 ] } },
{ "type": "Feature", "properties": { "CODATRAC": "R040123", "JERARQUIA": "LOCAL", "CATEGORIA": "ACONTECIMIENTOS PROGRAMADOS", "TIPO": "EVENTOS MISCELÁNEOS", "SUBTIPO": "CARNAVAL O FIESTA COSTUMBRISTA", "NOMBRE": "FIESTA DE LA VENDIMIA DE OVALLE", "REGION": "REGIÓN DE COQUIMBO", "PROVINCIA": "LIMARI", "COMUNA": "OVALLE", "LOCALIDAD": "OVALLE", "DIRECCION": "", "TELEFONO": "", "PROPIEDAD": "PUBLICA", "ADMINISTRA": "PUBLICA", "DISTCR": "88", "CR": "LA SERENA", "DISTCC": "0", "CC": "OVALLE", "LOC_URBANA": "OVALLE", "ESTACIONAL": "26 AL 28 DE FEBRERO", "USO_TUR": "ACTUAL", "DEMANDA": "LOCAL, REGIONAL NACIONAL", "SERVICIOS": "SERVICIOS COMPLETOS", "COD_REG": 4, "COD_PROV": 43, "COD_COM": 4301, "DESCRIPCIO": "La Fiesta de la Vendimia de Ovalle es una actividad organizada por Municipalidad de Ovalle, con la idea de destacar el potencial que posee el Valle del Limarí en la producción de vinos y piscos.", "ESTADO_1": "BUENA", "POINT_X": -71.20263905, "POINT_Y": -30.603353974800001 }, "geometry": { "type": "Point", "coordinates": [ -71.202639049999959, -30.603353974827254, 0.0 ] } },
{ "type": "Feature", "properties": { "CODATRAC": "R040137", "JERARQUIA": "LOCAL", "CATEGORIA": "ACONTECIMIENTOS PROGRAMADOS", "TIPO": "EVENTOS MISCELÁNEOS", "SUBTIPO": "CARNAVAL O FIESTA COSTUMBRISTA", "NOMBRE": "FIESTA DEL CABRITO", "REGION": "REGIÓN DE COQUIMBO", "PROVINCIA": "LIMARI", "COMUNA": "OVALLE", "LOCALIDAD": "OVALLE", "DIRECCION": "", "TELEFONO": "", "PROPIEDAD": "PUBLICA", "ADMINISTRA": "PUBLICA", "DISTCR": "88", "CR": "LA SERENA", "DISTCC": "0", "CC": "OVALLE", "LOC_URBANA": "OVALLE", "ESTACIONAL": "FEBRERO", "USO_TUR": "ACTUAL", "DEMANDA": "LOCAL, REGIONAL, NACIONAL", "SERVICIOS": "SERVICIOS COMPLETOS", "COD_REG": 4, "COD_PROV": 43, "COD_COM": 4301, "DESCRIPCIO": "Se celebra en el Parue Tamelcura, ubicado a 19 km al este de Ovalle. Es una autentica celebración gastronomica en torno a productos relacionados con el ganado caprino de gran tradición en la zona.", "ESTADO_1": "BUENA", "POINT_X": -71.042909066000007, "POINT_Y": -30.693105593799999 }, "geometry": { "type": "Point", "coordinates": [ -71.042909065999936, -30.693105593828687, 0.0 ] } },
{ "type": "Feature", "properties": { "CODATRAC": "R040138", "JERARQUIA": "REGIONAL", "CATEGORIA": "ACONTECIMIENTOS PROGRAMADOS", "TIPO": "EVENTOS MISCELÁNEOS", "SUBTIPO": "FIESTA RELIGIOSA", "NOMBRE": "FIESTA DEL NIÑO DIOS DE SOTAQUI", "REGION": "REGIÓN DE COQUIMBO", "PROVINCIA": "LIMARI", "COMUNA": "OVALLE", "LOCALIDAD": "SOTAQUI", "DIRECCION": "", "TELEFONO": "(53) 2661238", "PROPIEDAD": "PRIVADA", "ADMINISTRA": "PRIVADA", "DISTCR": "99", "CR": "LA SERENA", "DISTCC": "11", "CC": "OVALLE", "LOC_URBANA": "OVALLE", "ESTACIONAL": "ENERO", "USO_TUR": "ACTUAL", "DEMANDA": "LOCAL, REGIONAL", "SERVICIOS": "SERVICIOS COMPLETOS", "COD_REG": 4, "COD_PROV": 43, "COD_COM": 4301, "DESCRIPCIO": "En Sotaqui la fiesta se realiza en honor de la imagen del Niño Dios. Actualmente a la fiesta concurren unas diez a doce hermandades de bailes chinos, turbantes y danzantes provenientes de toda la cuarta región.", "ESTADO_1": "BUENA", "POINT_X": -71.121132586000002, "POINT_Y": -30.631572970800001 }, "geometry": { "type": "Point", "coordinates": [ -71.121132585999987, -30.631572970827712, 0.0 ] } },
{ "type": "Feature", "properties": { "CODATRAC": "R040165", "JERARQUIA": "LOCAL", "CATEGORIA": "REALIZACIONES TÉCNICAS Y CIENTÍFICAS CONTEMPORÁNEAS Y CULTURALES HISTÓRICAS", "TIPO": "OBRAS DE ARTE Y TÉCNICA", "SUBTIPO": "ARQUITECTURA", "NOMBRE": "IGLESIA DEL NIÑO JESÚS DE SOTAQUI (MH)", "REGION": "REGIÓN DE COQUIMBO", "PROVINCIA": "LIMARI", "COMUNA": "OVALLE", "LOCALIDAD": "SOTAQUI", "DIRECCION": "CALLE BILBAO, FRENTE A LA PLAZA, SOTAQUI", "TELEFONO": "(53) 623954", "PROPIEDAD": "PRIVADA", "ADMINISTRA": "PRIVADA", "DISTCR": "99", "CR": "LA SERENA", "DISTCC": "11", "CC": "OVALLE", "LOC_URBANA": "OVALLE", "ESTACIONAL": "CERRADA", "USO_TUR": "ACTUAL EN RESTAURACIÓN", "DEMANDA": "LOCAL", "SERVICIOS": "AGUA POTABLE, ELECTRICIDAD", "COD_REG": 4, "COD_PROV": 43, "COD_COM": 4301, "DESCRIPCIO": "Declarada Monumento Histórico D.S. 1079 del 18/07/2006. La Iglesia de Sotaquí fue construida a fines del S. XIX, es de estilo Corintio y sus tres grandes torres resaltan sobren las rusticas casas del poblado.", "ESTADO_1": "MALA", "POINT_X": -71.120777251999996, "POINT_Y": -30.6315426858 }, "geometry": { "type": "Point", "coordinates": [ -71.120777251999982, -30.631542685827682, 0.0 ] } },
{ "type": "Feature", "properties": { "CODATRAC": "R040171", "JERARQUIA": "NACIONAL", "CATEGORIA": "REALIZACIONES TÉCNICAS Y CIENTÍFICAS CONTEMPORÁNEAS Y CULTURALES HISTÓRICAS", "TIPO": "OBRAS DE ARTE Y TÉCNICA", "SUBTIPO": "ARQUITECTURA", "NOMBRE": "IGLESIA SAN ANTONIO DE BARRAZA (MH)", "REGION": "REGIÓN DE COQUIMBO", "PROVINCIA": "LIMARI", "COMUNA": "OVALLE", "LOCALIDAD": "BARRAZA", "DIRECCION": "", "TELEFONO": "(53) 661238", "PROPIEDAD": "PRIVADA", "ADMINISTRA": "PRIVADA", "DISTCR": "118", "CR": "LA SERENA", "DISTCC": "30", "CC": "OVALLE", "LOC_URBANA": "OVALLE", "ESTACIONAL": "TODO EL AÑO", "USO_TUR": "ACTUAL CON RESTRICCIÓN", "DEMANDA": "LOCAL, REGIONAL, NACIONAL", "SERVICIOS": "AGUA POTABLE, ELECTRICIDAD", "COD_REG": 4, "COD_PROV": 43, "COD_COM": 4301, "DESCRIPCIO": "Declarada Monumento Histórico D.S. 1025 del 14/12/1977. La primera edificación con características propias de la época, data de 1648. Resalta de esta construcción una antigua puerta de pino oregón con clavos de cobre elaborados a golpe de martillo.", "ESTADO_1": "REGULAR", "POINT_X": -71.481491496999993, "POINT_Y": -30.656120853800001 }, "geometry": { "type": "Point", "coordinates": [ -71.481491496999979, -30.65612085382806, 0.0 ] } },
{ "type": "Feature", "properties": { "CODATRAC": "R040172", "JERARQUIA": "REGIONAL", "CATEGORIA": "REALIZACIONES TÉCNICAS Y CIENTÍFICAS CONTEMPORÁNEAS Y CULTURALES HISTÓRICAS", "TIPO": "OBRAS DE ARTE Y TÉCNICA", "SUBTIPO": "ARQUITECTURA", "NOMBRE": "IGLESIA SAN VICENTE FERRER (MH)", "REGION": "REGIÓN DE COQUIMBO", "PROVINCIA": "LIMARI", "COMUNA": "OVALLE", "LOCALIDAD": "OVALLE", "DIRECCION": "LIBERTAD 260, OVALLE", "TELEFONO": "(53) 620103", "PROPIEDAD": "PRIVADA", "ADMINISTRA": "PRIVADA", "DISTCR": "88", "CR": "LA SERENA", "DISTCC": "0", "CC": "OVALLE", "LOC_URBANA": "OVALLE", "ESTACIONAL": "TODO EL AÑO", "USO_TUR": "ACTUAL CON RESTRICCIÓN", "DEMANDA": "LOCAL, REGIONAL", "SERVICIOS": "AGUA POTABLE, ELECTRICIDAD", "COD_REG": 4, "COD_PROV": 43, "COD_COM": 4301, "DESCRIPCIO": "La iglesia de San Vicente Ferrer de Ovalle, se ubica frente a la plaza de la ciudad. Fue declarada Monumento Histórico el año 1981 y sus comienzos se remontan al año 1824.", "ESTADO_1": "BUENA", "POINT_X": -71.203392211999997, "POINT_Y": -30.602457391800002 }, "geometry": { "type": "Point", "coordinates": [ -71.203392211999983, -30.602457391827237, 0.0 ] } },
{ "type": "Feature", "properties": { "CODATRAC": "R040183", "JERARQUIA": "REGIONAL", "CATEGORIA": "FOLKLORE", "TIPO": "ARQUITECTURA POPULAR ESPONTÁNEA", "SUBTIPO": "PUEBLO O ALDEA TRADICIONAL", "NOMBRE": "LA CHIMBA", "REGION": "REGIÓN DE COQUIMBO", "PROVINCIA": "LIMARI", "COMUNA": "OVALLE", "LOCALIDAD": "LA CHIMBA", "DIRECCION": "A 6 KM AL OESTE DE OVALLE", "TELEFONO": "(53) 661238", "PROPIEDAD": "PÚBLICA", "ADMINISTRA": "PÚBLICA", "DISTCR": "94", "CR": "LA SERENA", "DISTCC": "6", "CC": "OVALLE", "LOC_URBANA": "OVALLE", "ESTACIONAL": "TODO EL AÑO", "USO_TUR": "ACTUAL", "DEMANDA": "LOCAL, REGIONAL", "SERVICIOS": "AGUA POTABLE, ELECTRICIDAD", "COD_REG": 4, "COD_PROV": 43, "COD_COM": 4301, "DESCRIPCIO": "Es un pintoresco pueblo cuya principal actividad es la horticultura, que se remonta al tiempo cuando los incas la usaban como mitimae (pequeña comunidad agrícola). La llamaron La Chimba que en lengua quechua significa ‘al otro lado del río’.", "ESTADO_1": "BUENA", "POINT_X": -71.231739152000003, "POINT_Y": -30.641681971800001 }, "geometry": { "type": "Point", "coordinates": [ -71.231739151999989, -30.641681971827854, 0.0 ] } },
{ "type": "Feature", "properties": { "CODATRAC": "R040205", "JERARQUIA": "REGIONAL", "CATEGORIA": "MUSEOS MANIFESTACIONES CULTURALES Y LUGARES DE INTERÉS HISTÓRICO O CULTURAL", "TIPO": "MUSEO Y SALA DE EXPOSICIÓN MUSEOGRÁFICA", "SUBTIPO": "MUSEO", "NOMBRE": "MUSEO ARQUEOLÓGICO DEL LIMARI", "REGION": "REGIÓN DE COQUIMBO", "PROVINCIA": "LIMARI", "COMUNA": "OVALLE", "LOCALIDAD": "OVALLE", "DIRECCION": "COVARRUBIAS ESQ ANTOFAGASTA, OVALLE", "TELEFONO": "(53) 433680", "PROPIEDAD": "PÚBLICA", "ADMINISTRA": "PÚBLICA", "DISTCR": "88", "CR": "LA SERENA", "DISTCC": "0", "CC": "OVALLE", "LOC_URBANA": "OVALLE", "ESTACIONAL": "TODO EL AÑO", "USO_TUR": "ACTUAL", "DEMANDA": "LOCAL, REGIONAL", "SERVICIOS": "AGUA POTABLE, ELECTRICIDAD", "COD_REG": 4, "COD_PROV": 43, "COD_COM": 4301, "DESCRIPCIO": "Se ubica al interior de la ex-Estación de Ferrocarriles de Ovalle, actualmente denominado Centro Cultural Guillermo Durruty Álvarez. El Museo del Limarí fue creado por la Sociedad Arqueológica de Ovalle el 17 de septiembre de 1963.", "ESTADO_1": "BUENA", "POINT_X": -71.195558235999997, "POINT_Y": -30.599577018800002 }, "geometry": { "type": "Point", "coordinates": [ -71.195558235999954, -30.599577018827151, 0.0 ] } },
{ "type": "Feature", "properties": { "CODATRAC": "R040230", "JERARQUIA": "REGIONAL", "CATEGORIA": "REALIZACIONES TÉCNICAS Y CIENTÍFICAS CONTEMPORÁNEAS Y CULTURALES HISTÓRICAS", "TIPO": "DESARROLLO URBANO", "SUBTIPO": "CIUDAD", "NOMBRE": "OVALLE", "REGION": "REGIÓN DE COQUIMBO", "PROVINCIA": "LIMARI", "COMUNA": "OVALLE", "LOCALIDAD": "OVALLE", "DIRECCION": "A 33 KM AL SURESTE DE MONTE PATRIA", "TELEFONO": "(53) 661238", "PROPIEDAD": "PÚBLICA", "ADMINISTRA": "PÚBLICA", "DISTCR": "88", "CR": "LA SERENA", "DISTCC": "0", "CC": "OVALLE", "LOC_URBANA": "OVALLE", "ESTACIONAL": "TODO EL AÑO", "USO_TUR": "ACTUAL", "DEMANDA": "LOCAL, REGIONAL", "SERVICIOS": "AGUA POTABLE, ELECTRICIDAD", "COD_REG": 4, "COD_PROV": 43, "COD_COM": 4301, "DESCRIPCIO": "Ovalle, también conocida como La Perla del Limarí, es una ciudad y la comuna capital de la provincia de Limarí. Nacida como villa, la ciudad fue fundada en 1831, bajo el gobierno provisorio de José Tomás Ovalle, a quién debe su nombre.", "ESTADO_1": "BUENA", "POINT_X": -71.202950083999994, "POINT_Y": -30.603195545799998 }, "geometry": { "type": "Point", "coordinates": [ -71.202950083999951, -30.603195545827234, 0.0 ] } },
{ "type": "Feature", "properties": { "CODATRAC": "R040237", "JERARQUIA": "NACIONAL", "CATEGORIA": "SITIOS NATURALES", "TIPO": "ÁREA PROTEGIDA Y LUGARES DE OBSERVACIÓN DE FLORA Y FAUNA", "SUBTIPO": "ÁREA SILVESTRE PROTEGIDA DEL ESTADO (ASPE)", "NOMBRE": "PARQUE NACIONAL FRAY JORGE", "REGION": "REGIÓN DE COQUIMBO", "PROVINCIA": "LIMARI", "COMUNA": "OVALLE", "LOCALIDAD": "ALTOS DE TALINAY", "DIRECCION": "", "TELEFONO": "(53) 620058", "PROPIEDAD": "PÚBLICA", "ADMINISTRA": "PÚBLICA", "DISTCR": "111", "CR": "LA SERENA", "DISTCC": "90", "CC": "OVALLE", "LOC_URBANA": "", "ESTACIONAL": "TODO EL AÑO", "USO_TUR": "ACTUAL", "DEMANDA": "LOCAL, REGIONAL, NACIONAL", "SERVICIOS": "AGUA POTABLE, ELECTRICIDAD", "COD_REG": 4, "COD_PROV": 43, "COD_COM": 4301, "DESCRIPCIO": "Fue creado en 1941, durante el gobierno de Juan Antonio Ríos con el fin de preservar uno de los ecosistemas más exclusivos de Chile. El Parque se ubica en el sector costero, muy cerca del Desierto de Atacama.", "ESTADO_1": "BUENA", "POINT_X": -71.682713708999998, "POINT_Y": -30.662519657800001 }, "geometry": { "type": "Point", "coordinates": [ -71.682713708999984, -30.662519657828177, 0.0 ] } },
{ "type": "Feature", "properties": { "CODATRAC": "R040247", "JERARQUIA": "LOCAL", "CATEGORIA": "SITIOS NATURALES", "TIPO": "COSTA", "SUBTIPO": "PLAYA O BALNEARIO", "NOMBRE": "PLAYA AL SUR DEL RÍO LIMARI", "REGION": "REGIÓN DE COQUIMBO", "PROVINCIA": "LIMARI", "COMUNA": "OVALLE", "LOCALIDAD": "DESEMBOCADURA DEL RÍO LIMARÍ", "DIRECCION": "", "TELEFONO": "", "PROPIEDAD": "PÚBLICA", "ADMINISTRA": "PÚBLICA", "DISTCR": "0", "CR": "LA SERENA", "DISTCC": "0", "CC": "OVALLE", "LOC_URBANA": "OVALLE", "ESTACIONAL": "TODO EL AÑO", "USO_TUR": "ACTUAL", "DEMANDA": "LOCAL", "SERVICIOS": "SIN SERVICIOS", "COD_REG": 4, "COD_PROV": 43, "COD_COM": 4301, "DESCRIPCIO": "Playa que se genera al sur de la desembocadura del Río Limarí al llegar al Oceano Pacífico.", "ESTADO_1": "BUENA", "POINT_X": -71.698755722000001, "POINT_Y": -30.734346863799999 }, "geometry": { "type": "Point", "coordinates": [ -71.698755721999987, -30.734346863829273, 0.0 ] } },
{ "type": "Feature", "properties": { "CODATRAC": "R040282", "JERARQUIA": "REGIONAL", "CATEGORIA": "REALIZACIONES TÉCNICAS Y CIENTÍFICAS CONTEMPORÁNEAS Y CULTURALES HISTÓRICAS", "TIPO": "OBRAS DE ARTE Y TÉCNICA", "SUBTIPO": "REALIZACIÓN URBANA", "NOMBRE": "PLAZA DE ARMAS DE OVALLE", "REGION": "REGIÓN DE COQUIMBO", "PROVINCIA": "LIMARI", "COMUNA": "OVALLE", "LOCALIDAD": "OVALLE", "DIRECCION": "M. AGUIRRE ESQ. LIBERTAD", "TELEFONO": "(53) 661238", "PROPIEDAD": "PÚBLICA", "ADMINISTRA": "PÚBLICA", "DISTCR": "88", "CR": "LA SERENA", "DISTCC": "0", "CC": "OVALLE", "LOC_URBANA": "OVALLE", "ESTACIONAL": "TODO EL AÑO", "USO_TUR": "ACTUAL", "DEMANDA": "LOCAL, REGIONAL", "SERVICIOS": "AGUA POTABLE, ELECTRICIDAD", "COD_REG": 4, "COD_PROV": 43, "COD_COM": 4301, "DESCRIPCIO": "El diseño fue elaborado por Gastón Cea y está rodeada de palmeras Phoenix, además de otras especies que hacen que se asemeje a un jardín botánico. Un punto principal de la Plaza de Armas de Ovalle, es el llamado Quiosco de la Plaza.", "ESTADO_1": "BUENA", "POINT_X": -71.202884476999998, "POINT_Y": -30.603061348800001 }, "geometry": { "type": "Point", "coordinates": [ -71.202884476999941, -30.603061348827268, 0.0 ] } },
{ "type": "Feature", "properties": { "CODATRAC": "R040307", "JERARQUIA": "REGIONAL", "CATEGORIA": "FOLKLORE", "TIPO": "ARQUITECTURA POPULAR ESPONTÁNEA", "SUBTIPO": "PUEBLO O ALDEA TRADICIONAL", "NOMBRE": "SALALA", "REGION": "REGIÓN DE COQUIMBO", "PROVINCIA": "LIMARI", "COMUNA": "OVALLE", "LOCALIDAD": "SALALA", "DIRECCION": "A 3 KM AL NORTE DE BARRAZA", "TELEFONO": "(53) 661238", "PROPIEDAD": "PÚBLICA", "ADMINISTRA": "PÚBLICA", "DISTCR": "98", "CR": "LA SERENA", "DISTCC": "32", "CC": "OVALLE", "LOC_URBANA": "BARRAZA", "ESTACIONAL": "TODO EL AÑO", "USO_TUR": "ACTUAL", "DEMANDA": "LOCAL, REGIONAL", "SERVICIOS": "AGUA POTABLE, ELECTRICIDAD", "COD_REG": 4, "COD_PROV": 43, "COD_COM": 4301, "DESCRIPCIO": "Se encuentra por la orilla del río Limarí. Está habitado por pequeños agricultores que se dedican principalmente a la plantación de hortalizas y crianza de ganado caprino, son éstos los llamados ‘cabreros’, personajes autóctonos de esta regi", "ESTADO_1": "BUENA", "POINT_X": -71.520039940999993, "POINT_Y": -30.685058700799999 }, "geometry": { "type": "Point", "coordinates": [ -71.520039940999936, -30.68505870082852, 0.0 ] } },
{ "type": "Feature", "properties": { "CODATRAC": "R040310", "JERARQUIA": "LOCAL", "CATEGORIA": "FOLKLORE", "TIPO": "ARQUITECTURA POPULAR ESPONTÁNEA", "SUBTIPO": "PUEBLO O ALDEA TRADICIONAL", "NOMBRE": "SAMO BAJO", "REGION": "REGIÓN DE COQUIMBO", "PROVINCIA": "LIMARI", "COMUNA": "OVALLE", "LOCALIDAD": "SAMO BAJO", "DIRECCION": "14 KM AL ESTE DE OVALLE", "TELEFONO": "", "PROPIEDAD": "PÚBLICA", "ADMINISTRA": "PÚBLICA", "DISTCR": "98", "CR": "LA SERENA", "DISTCC": "14", "CC": "OVALLE", "LOC_URBANA": "OVALLE", "ESTACIONAL": "TODO EL AÑO", "USO_TUR": "ACTUAL", "DEMANDA": "LOCAL", "SERVICIOS": "", "COD_REG": 4, "COD_PROV": 43, "COD_COM": 4301, "DESCRIPCIO": "Caserío situado en la margen del río Guamalata como a 30 kilómetros más abajo de Samo Alto. Dista unos 14 kilómetros hacia el este de la ciudad de Ovalle.", "ESTADO_1": "BUENA", "POINT_X": -71.119678523999994, "POINT_Y": -30.532223468800002 }, "geometry": { "type": "Point", "coordinates": [ -71.119678523999937, -30.532223468826135, 0.0 ] } },
{ "type": "Feature", "properties": { "CODATRAC": "R040320", "JERARQUIA": "NACIONAL", "CATEGORIA": "FOLKLORE", "TIPO": "ARQUITECTURA POPULAR ESPONTÁNEA", "SUBTIPO": "PUEBLO O ALDEA TRADICIONAL", "NOMBRE": "SOTAQUI", "REGION": "REGIÓN DE COQUIMBO", "PROVINCIA": "LIMARI", "COMUNA": "OVALLE", "LOCALIDAD": "SOTAQUI", "DIRECCION": "A 11 KM AL ESTE DE OVALLE", "TELEFONO": "(53) 661238", "PROPIEDAD": "PÚBLICA", "ADMINISTRA": "PÚBLICA", "DISTCR": "99", "CR": "LA SERENA", "DISTCC": "11", "CC": "OVALLE", "LOC_URBANA": "OVALLE", "ESTACIONAL": "TODO EL AÑO", "USO_TUR": "ACTUAL", "DEMANDA": "LOCAL, REGIONAL, NACIONAL", "SERVICIOS": "AGUA POTABLE, ELECTRICIDAD", "COD_REG": 4, "COD_PROV": 43, "COD_COM": 4301, "DESCRIPCIO": "El lugar es conocido gracias a una de las Fiestas Religiosas más famosas de Chile, y que allí se realiza en honor de la imagen del Niño Dios encontrada en el siglo XIX en la Quebrada Los Naranjos, cerca de Sotaquí.", "ESTADO_1": "BUENA", "POINT_X": -71.120870514000003, "POINT_Y": -30.632470300800001 }, "geometry": { "type": "Point", "coordinates": [ -71.120870513999932, -30.63247030082772, 0.0 ] } },
{ "type": "Feature", "properties": { "CODATRAC": "R040323", "JERARQUIA": "NACIONAL", "CATEGORIA": "SITIOS NATURALES", "TIPO": "TERMA", "SUBTIPO": "FUENTE Y CENTRO TERMAL", "NOMBRE": "TERMAS DE SOCOS", "REGION": "REGIÓN DE COQUIMBO", "PROVINCIA": "LIMARI", "COMUNA": "OVALLE", "LOCALIDAD": "TERMAS DE SOCOS", "DIRECCION": "A 38 KM AL SURESTE DE OVALLE", "TELEFONO": "(53) 1982505", "PROPIEDAD": "PRIVADA", "ADMINISTRA": "PRIVADA", "DISTCR": "101", "CR": "LA SERENA", "DISTCC": "38", "CC": "OVALLE", "LOC_URBANA": "OVALLE", "ESTACIONAL": "TODO EL AÑO", "USO_TUR": "ACTUAL", "DEMANDA": "LOCAL, REGIONAL, NACIONAL", "SERVICIOS": "AGUA POTABLE, ELECTRICIDAD", "COD_REG": 4, "COD_PROV": 43, "COD_COM": 4301, "DESCRIPCIO": "Características por ser las más cercanas a la costa, las Termas de Socos son un reconfortante atractivo para quienes visiten la zona. Las aguas termales son las ideales para calmar dolencias reumáticas y nerviosas.", "ESTADO_1": "BUENA", "POINT_X": -71.493071381999997, "POINT_Y": -30.731609343799999 }, "geometry": { "type": "Point", "coordinates": [ -71.493071381999982, -30.731609343829245, 0.0 ] } },
{ "type": "Feature", "properties": { "CODATRAC": "R040334", "JERARQUIA": "REGIONAL", "CATEGORIA": "SITIOS NATURALES", "TIPO": "MONTAÑA", "SUBTIPO": "VALLE Y QUEBRADA", "NOMBRE": "VALLE DE LIMARI", "REGION": "REGIÓN DE COQUIMBO", "PROVINCIA": "LIMARI", "COMUNA": "OVALLE", "LOCALIDAD": "VALLE DE LIMARI", "DIRECCION": "A 88 KM AL SURESTE DE LA SERENA", "TELEFONO": "(53) 661238", "PROPIEDAD": "PÚBLICA", "ADMINISTRA": "PÚBLICA", "DISTCR": "88", "CR": "LA SERENA", "DISTCC": "0", "CC": "OVALLE", "LOC_URBANA": "OVALLE", "ESTACIONAL": "TODO EL AÑO", "USO_TUR": "ACTUAL", "DEMANDA": "LOCAL, REGIONAL", "SERVICIOS": "AGUA POTABLE, ELECTRICIDAD", "COD_REG": 4, "COD_PROV": 43, "COD_COM": 4301, "DESCRIPCIO": "El imponente Valle del Limarí es un territorio conformado por decenas de pequeños valles y quebradas con sus propios ríos y esteros, los cuales están intercomunicados entre sí y que al final todos se vuelcan hacia el Océano Pacífico.", "ESTADO_1": "BUENA", "POINT_X": -71.272617916000002, "POINT_Y": -30.633883526799998 }, "geometry": { "type": "Point", "coordinates": [ -71.272617915999945, -30.633883526827738, 0.0 ] } },
{ "type": "Feature", "properties": { "CODATRAC": "R040339", "JERARQUIA": "NACIONAL", "CATEGORIA": "MUSEOS MANIFESTACIONES CULTURALES Y LUGARES DE INTERÉS HISTÓRICO O CULTURAL", "TIPO": "RUINA O LUGAR ARQUEOLÓGICO", "SUBTIPO": "RUINA O LUGAR ARQUEOLÓGICO", "NOMBRE": "VALLE EL ENCANTO (MH)", "REGION": "REGIÓN DE COQUIMBO", "PROVINCIA": "LIMARI", "COMUNA": "OVALLE", "LOCALIDAD": "QUEBRADA LAS PEÑAS", "DIRECCION": "A 24 KM AL SUROESTE DE OVALLE", "TELEFONO": "(53) 661238", "PROPIEDAD": "PÚBLICA", "ADMINISTRA": "PÚBLICA", "DISTCR": "112", "CR": "LA SERENA", "DISTCC": "24", "CC": "OVALLE", "LOC_URBANA": "OVALLE", "ESTACIONAL": "TODO EL AÑO", "USO_TUR": "ACTUAL", "DEMANDA": "LOCAL, REGIONAL, NACIONAL", "SERVICIOS": "SIN SERVICIOS", "COD_REG": 4, "COD_PROV": 43, "COD_COM": 4301, "DESCRIPCIO": "Declarado Monumento Histórico D.S. 158 del 05/02/1973. La cuenca del río Limarí es quizá la más rica en grabados o petroglifos del Norte Chico, configurándose en ella un estilo de arte rupestre -el Estilo Limarí-.", "ESTADO_1": "REGULAR", "POINT_X": -71.377343002000003, "POINT_Y": -30.7053060348 }, "geometry": { "type": "Point", "coordinates": [ -71.377343001999975, -30.70530603482883, 0.0 ] } },
{ "type": "Feature", "properties": { "CODATRAC": "R040340", "JERARQUIA": "LOCAL", "CATEGORIA": "SITIOS NATURALES", "TIPO": "MONTAÑA", "SUBTIPO": "VALLE Y QUEBRADA", "NOMBRE": "VALLE HUAMALATA", "REGION": "REGIÓN DE COQUIMBO", "PROVINCIA": "LIMARI", "COMUNA": "OVALLE", "LOCALIDAD": "VALLE HUAMALATA", "DIRECCION": "", "TELEFONO": "", "PROPIEDAD": "PÚBLICA", "ADMINISTRA": "PÚBLICA", "DISTCR": "0", "CR": "LA SERENA", "DISTCC": "0", "CC": "OVALLE", "LOC_URBANA": "HUAMALATA", "ESTACIONAL": "TODO EL AÑO", "USO_TUR": "ACTUAL", "DEMANDA": "LOCAL", "SERVICIOS": "", "COD_REG": 4, "COD_PROV": 43, "COD_COM": 4301, "DESCRIPCIO": "Valle entre el poblado de Huamalata y el sector de Los Peñones. Posee una densa vegetación que se alimenta de pequeños humedales de sector.", "ESTADO_1": "BUENA", "POINT_X": -71.174194357000005, "POINT_Y": -30.575426835799998 }, "geometry": { "type": "Point", "coordinates": [ -71.174194356999976, -30.575426835826811, 0.0 ] } },
{ "type": "Feature", "properties": { "CODATRAC": "R040227", "JERARQUIA": "NACIONAL", "CATEGORIA": "REALIZACIONES TÉCNICAS Y CIENTÍFICAS CONTEMPORÁNEAS Y CULTURALES HISTÓRICAS", "TIPO": "CENTRO CIENTÍFICO", "SUBTIPO": "OBSERVATORIO ASTRONÓMICO", "NOMBRE": "OBSERVATORIO OVALLE CASINO & RESORT", "REGION": "REGIÓN DE COQUIMBO", "PROVINCIA": "LIMARÍ", "COMUNA": "OVALLE", "LOCALIDAD": "OVALLE", "DIRECCION": "Avenida Manuel Peñafiel 2711, Ovalle", "TELEFONO": "+56 53 2655104 – 101 - 100", "PROPIEDAD": "PRIVADA", "ADMINISTRA": "PRIVADA", "DISTCR": "80", "CR": "LA SERENA", "DISTCC": "3", "CC": "OVALLE", "LOC_URBANA": "OVALLE", "ESTACIONAL": "TODO EL AÑO", "USO_TUR": "ACTUAL", "DEMANDA": "LOCAL, REGIONAL, NACIONAL", "SERVICIOS": "AGUA POTABLE, ELECTRICIDAD", "COD_REG": 4, "COD_PROV": 43, "COD_COM": 4301, "DESCRIPCIO": "Se pueden observar las estrellas, constelaciones, planetas, nebulosas y mucho más. El moderno telescopio computarizado de 9″1/4 de diámetro permite apreciar magníficas imágenes de uno de los cielos más limpios de Chile.", "ESTADO_1": "BUENA", "POINT_X": -71.1849103232, "POINT_Y": -30.573698 }, "geometry": { "type": "Point", "coordinates": [ -71.184910323233936, -30.573698, 0.0 ] } }
]
}
