{
"type": "FeatureCollection",
"crs": { "type": "name", "properties": { "name": "urn:ogc:def:crs:EPSG::4979" } },
"features": [
{ "type": "Feature", "properties": { "CODATRAC": "R050002", "JERARQUIA": "REGIONAL", "CATEGORIA": "SITIOS NATURALES", "TIPO": "COSTA", "SUBTIPO": "ACANTILADO", "NOMBRE": "ACANTILADOS DE PAPUDO", "REGION": "REGIÓN DE VALPARAÍSO", "PROVINCIA": "PETORCA", "COMUNA": "PAPUDO", "LOCALIDAD": "PAPUDO", "DIRECCION": "", "TELEFONO": "", "PROPIEDAD": "PÚBLICA", "ADMINISTRA": "PÚBLICA", "DISTCR": "0", "CR": "VALPARAÍSO", "DISTCC": "0", "CC": "PAPUDO", "LOC_URBANA": "PAPUDO", "ESTACIONAL": "TODO EL AÑO", "USO_TUR": "ACTUAL", "DEMANDA": "LOCAL, REGIONAL", "SERVICIOS": "", "COD_REG": 5, "COD_PROV": 54, "COD_COM": 5403, "DESCRIPCIO": "", "ESTADO_1": "BUENA", "POINT_X": -71.471083617999994, "POINT_Y": -32.508241334799997 }, "geometry": { "type": "Point", "coordinates": [ -71.471083618014404, -32.50824133476965, 0.0 ] } },
{ "type": "Feature", "properties": { "CODATRAC": "R050056", "JERARQUIA": "NACIONAL", "CATEGORIA": "SITIOS NATURALES", "TIPO": "COSTA", "SUBTIPO": "PLAYA O BALNEARIO", "NOMBRE": "BALNEARIO PAPUDO", "REGION": "REGIÓN DE VALPARAÍSO", "PROVINCIA": "PETORCA", "COMUNA": "PAPUDO", "LOCALIDAD": "PAPUDO", "DIRECCION": "100 KM DE VALPARAÍSO", "TELEFONO": "(33) 791115", "PROPIEDAD": "PÚBLICA", "ADMINISTRA": "PÚBLICA", "DISTCR": "100", "CR": "VALPARAÍSO", "DISTCC": "0", "CC": "PAPUDO", "LOC_URBANA": "PAPUDO", "ESTACIONAL": "TODO EL AÑO", "USO_TUR": "ACTUAL", "DEMANDA": "LOCAL, REGIONAL, NACIONAL", "SERVICIOS": "AGUA POTABLE, ELECTRICIDAD", "COD_REG": 5, "COD_PROV": 54, "COD_COM": 5403, "DESCRIPCIO": "Papudo está entre los balnearios más antiguos de la Región. Fundado en 1857. Cuenta con hoteles, moteles, residenciales, restaurantes, discotecas, club de yates y dos playas de aguas claras y arenas finas.", "ESTADO_1": "BUENA", "POINT_X": -71.446256091799995, "POINT_Y": -32.507464343000002 }, "geometry": { "type": "Point", "coordinates": [ -71.446256091844987, -32.50746434300487, 0.0 ] } },
{ "type": "Feature", "properties": { "CODATRAC": "R050072", "JERARQUIA": "NACIONAL", "CATEGORIA": "SITIOS NATURALES", "TIPO": "COSTA", "SUBTIPO": "BAHÍA O CALETA", "NOMBRE": "CALETA PAPUDO", "REGION": "REGIÓN DE VALPARAÍSO", "PROVINCIA": "PETORCA", "COMUNA": "PAPUDO", "LOCALIDAD": "CALETA PAPUDO", "DIRECCION": "A 12 KM AL NOROESTE DE QUINQUIMO", "TELEFONO": "(33) 791115", "PROPIEDAD": "PRIVADA", "ADMINISTRA": "PRIVADA", "DISTCR": "82", "CR": "VALPARAÍSO", "DISTCC": "0", "CC": "PAPUDO", "LOC_URBANA": "QUINQUIMO", "ESTACIONAL": "TODO EL AÑO", "USO_TUR": "ACTUAL", "DEMANDA": "LOCAL, REGIONAL, NACIONAL", "SERVICIOS": "ELECTRICIDAD", "COD_REG": 5, "COD_PROV": 54, "COD_COM": 5403, "DESCRIPCIO": "La Caleta Papudo es otro de los atractivos del balneario del mismo nombre. En ella es posible encontrase con la llegada de botes de pesca artesanal y disfrutar del comercio de productos del mar, además de disfrutar del remodelado edificio de la Caleta.", "ESTADO_1": "BUENA", "POINT_X": -71.451082101300003, "POINT_Y": -32.503736279000002 }, "geometry": { "type": "Point", "coordinates": [ -71.451082101257839, -32.503736279005921, 0.0 ] } },
{ "type": "Feature", "properties": { "CODATRAC": "R050078", "JERARQUIA": "LOCAL", "CATEGORIA": "RUTAS Y CIRCUITOS TURÍSTICOS", "TIPO": "RUTA Y CIRCUITO", "SUBTIPO": "CIRCUITO TURÍSTICO", "NOMBRE": "CAMINO LONGOTOMA - LA LIGUA", "REGION": "REGIÓN DE VALPARAÍSO", "PROVINCIA": "PETORCA", "COMUNA": "PAPUDO", "LOCALIDAD": "LONGOTOMA", "DIRECCION": "", "TELEFONO": "", "PROPIEDAD": "PÚBLICA", "ADMINISTRA": "PÚBLICA", "DISTCR": "0", "CR": "VALPARAÍSO", "DISTCC": "0", "CC": "PAPUDO", "LOC_URBANA": "", "ESTACIONAL": "TODO EL AÑO", "USO_TUR": "ACTUAL", "DEMANDA": "LOCAL", "SERVICIOS": "", "COD_REG": 5, "COD_PROV": 54, "COD_COM": 5403, "DESCRIPCIO": "", "ESTADO_1": "BUENA", "POINT_X": -71.3292045, "POINT_Y": -32.427389091099997 }, "geometry": { "type": "Point", "coordinates": [ -71.329204499987554, -32.427389091133477, 0.0 ] } },
{ "type": "Feature", "properties": { "CODATRAC": "R050272", "JERARQUIA": "NACIONAL", "CATEGORIA": "REALIZACIONES TÉCNICAS Y CIENTÍFICAS CONTEMPORÁNEAS Y CULTURALES HISTÓRICAS", "TIPO": "OBRAS DE ARTE Y TÉCNICA", "SUBTIPO": "ARQUITECTURA", "NOMBRE": "IGLESIA NUESTRA SEÑORA DE LAS MERCEDES (MH)", "REGION": "REGIÓN DE VALPARAÍSO", "PROVINCIA": "PETORCA", "COMUNA": "PAPUDO", "LOCALIDAD": "PAPUDO", "DIRECCION": "FRENTE A LA PLAYA DE PAPUDO", "TELEFONO": "(33) 781060", "PROPIEDAD": "PRIVADA", "ADMINISTRA": "PRIVADA", "DISTCR": "91", "CR": "VALPARAÍSO", "DISTCC": "0", "CC": "PAPUDO", "LOC_URBANA": "PAPUDO", "ESTACIONAL": "TODO EL AÑO", "USO_TUR": "ACTUAL", "DEMANDA": "LOCAL, REGIONAL, NACIONAL", "SERVICIOS": "ELECTRICIDAD", "COD_REG": 5, "COD_PROV": 54, "COD_COM": 5403, "DESCRIPCIO": "Declarada Monumento Histórico D.S. 530 del 20/09/1995. La Iglesia Nuestra Señora de las Mercedes de Papudo fue inaugurada en 1918. De estilo neocolonial, es obra del arquitecto Alberto Cruz Montt, autor de construcciones muy importantes.", "ESTADO_1": "BUENA", "POINT_X": -71.449645687, "POINT_Y": -32.506452042699998 }, "geometry": { "type": "Point", "coordinates": [ -71.449645686998679, -32.50645204272746, 0.0 ] } },
{ "type": "Feature", "properties": { "CODATRAC": "R050366", "JERARQUIA": "REGIONAL", "CATEGORIA": "REALIZACIONES TÉCNICAS Y CIENTÍFICAS CONTEMPORÁNEAS Y CULTURALES HISTÓRICAS", "TIPO": "OBRAS DE ARTE Y TÉCNICA", "SUBTIPO": "ARQUITECTURA", "NOMBRE": "PALACIO RECART", "REGION": "REGIÓN DE VALPARAÍSO", "PROVINCIA": "PETORCA", "COMUNA": "PAPUDO", "LOCALIDAD": "PAPUDO", "DIRECCION": "CALLE CHINCHORRO 9, PAPUDO", "TELEFONO": "(33) 791115", "PROPIEDAD": "PRIVADA", "ADMINISTRA": "PRIVADA", "DISTCR": "91", "CR": "VALPARAÍSO", "DISTCC": "0", "CC": "PAPUDO", "LOC_URBANA": "PAPUDO", "ESTACIONAL": "TODO EL AÑO", "USO_TUR": "ACTUAL", "DEMANDA": "LOCAL, REGIONAL", "SERVICIOS": "AGUA POTABLE, ELECTRICIDAD", "COD_REG": 5, "COD_PROV": 54, "COD_COM": 5403, "DESCRIPCIO": "Construcción arquitectónica, diseñada por el afamado arquitecto Josué Smith Solar, destaca por su hermoso diseño y ubicación. Actualmente el edificio pertenece a la Municipalidad de Papudo y allí se encuentra la alcaldía.", "ESTADO_1": "BUENA", "POINT_X": -71.446873354100006, "POINT_Y": -32.5078581247 }, "geometry": { "type": "Point", "coordinates": [ -71.446873354121863, -32.507858124652557, 0.0 ] } },
{ "type": "Feature", "properties": { "CODATRAC": "R050501", "JERARQUIA": "LOCAL", "CATEGORIA": "SITIOS NATURALES", "TIPO": "PLANICIE", "SUBTIPO": "SALINA", "NOMBRE": "SALINAS DE PULLALLY", "REGION": "REGIÓN DE VALPARAÍSO", "PROVINCIA": "PETORCA", "COMUNA": "PAPUDO", "LOCALIDAD": "SALINAS DE PULLALLY", "DIRECCION": "A 15 KM DE LA LIGUA", "TELEFONO": "(33) 791115", "PROPIEDAD": "PRIVADA", "ADMINISTRA": "PRIVADA", "DISTCR": "91", "CR": "VALPARAÍSO", "DISTCC": "0", "CC": "PAPUDO", "LOC_URBANA": "PAPUDO", "ESTACIONAL": "TODO EL AÑO", "USO_TUR": "ACTUAL", "DEMANDA": "LOCAL", "SERVICIOS": "SIN SERVICIOS", "COD_REG": 5, "COD_PROV": 54, "COD_COM": 5403, "DESCRIPCIO": "La parte baja la compone la playa de Las Salinas de Pullally, donde existe un salar natural, dunas y vestigios de un asentamiento indígena como lo demuestran variados objetos encontrados en el sector.", "ESTADO_1": "BUENA", "POINT_X": -71.412791806800001, "POINT_Y": -32.416031350700003 }, "geometry": { "type": "Point", "coordinates": [ -71.412791806796292, -32.416031350666117, 0.0 ] } }
]
}
