{
"type": "FeatureCollection",
"crs": { "type": "name", "properties": { "name": "urn:ogc:def:crs:EPSG::4979" } },
"features": [
{ "type": "Feature", "properties": { "CODATRAC": "R060022", "JERARQUIA": "LOCAL", "CATEGORIA": "FOLKLORE", "TIPO": "ARQUITECTURA POPULAR ESPONTÁNEA", "SUBTIPO": "PUEBLO O ALDEA TRADICIONAL", "NOMBRE": "AUQUINCO", "REGION": "REGIÓN DEL LIBERTADOR BERNARDO O'HIGGINS", "PROVINCIA": "COLCHAGUA", "COMUNA": "CHÉPICA", "LOCALIDAD": "AUQUINCO", "DIRECCION": "A 20 KM AL SURESTE DE CHÉPICA", "TELEFONO": "(72) 2817213", "PROPIEDAD": "PÚBLICA", "ADMINISTRA": "PÚBLICA", "DISTCR": "90", "CR": "RANCAGUA", "DISTCC": "20", "CC": "CHÉPICA", "LOC_URBANA": "AUQUINCO", "ESTACIONAL": "TODO EL AÑO", "USO_TUR": "ACTUAL", "DEMANDA": "LOCAL", "SERVICIOS": "AGUA POTABLE, ELECTRICIDAD", "COD_REG": 6, "COD_PROV": 63, "COD_COM": 6302, "DESCRIPCIO": "Auquinco es un pequeño poblado ubicado en la VI región de Chile. Sus habitantes se dedican principalmente a la agricultura. El clima tiene marcadas las cuatro estaciones, con un verano caluroso y seco y un invierno lluvioso y frío.", "ESTADO_1": "BUENA", "POINT_X": -71.197397605000006, "POINT_Y": -34.761758471900002 }, "geometry": { "type": "Point", "coordinates": [ -71.197397604999935, -34.761758471884121, 0.0 ] } },
{ "type": "Feature", "properties": { "CODATRAC": "R060131", "JERARQUIA": "LOCAL", "CATEGORIA": "ACONTECIMIENTOS PROGRAMADOS", "TIPO": "EVENTOS MISCELÁNEOS", "SUBTIPO": "CARNAVAL O FIESTA COSTUMBRISTA", "NOMBRE": "FIESTA COSTUMBRISTA DE CHÉPICA", "REGION": "REGIÓN DEL LIBERTADOR BERNARDO O'HIGGINS", "PROVINCIA": "COLCHAGUA", "COMUNA": "CHÉPICA", "LOCALIDAD": "CHÉPICA", "DIRECCION": "PLAZA DE ARMAS DE CHÉPICA", "TELEFONO": "(72) 2817215", "PROPIEDAD": "PRIVADA", "ADMINISTRA": "PRIVADA", "DISTCR": "86", "CR": "RANCAGUA", "DISTCC": "0", "CC": "CHÉPICA", "LOC_URBANA": "CHÉPICA", "ESTACIONAL": "ENERO", "USO_TUR": "ACTUAL", "DEMANDA": "LOCAL", "SERVICIOS": "AGUA POTABLE, ELECTRICIDAD", "COD_REG": 6, "COD_PROV": 63, "COD_COM": 6302, "DESCRIPCIO": "5 noches de fiesta criolla con tradiciones y arte nacional.", "ESTADO_1": "BUENA", "POINT_X": -71.273796751999996, "POINT_Y": -34.728522025899998 }, "geometry": { "type": "Point", "coordinates": [ -71.273796751999953, -34.728522025883748, 0.0 ] } },
{ "type": "Feature", "properties": { "CODATRAC": "R060150", "JERARQUIA": "LOCAL", "CATEGORIA": "ACONTECIMIENTOS PROGRAMADOS", "TIPO": "EVENTOS MISCELÁNEOS", "SUBTIPO": "CARNAVAL O FIESTA COSTUMBRISTA", "NOMBRE": "FIESTA DE LA ESQUILA DE PAMPA DE LIMA", "REGION": "REGIÓN DEL LIBERTADOR BERNARDO O'HIGGINS", "PROVINCIA": "COLCHAGUA", "COMUNA": "CHÉPICA", "LOCALIDAD": "PAMPA DE LIMA", "DIRECCION": "PAMPA DE LIMA, CHÉPICA", "TELEFONO": "(72) 2817214", "PROPIEDAD": "PRIVADA", "ADMINISTRA": "PRIVADA", "DISTCR": "86", "CR": "RANCAGUA", "DISTCC": "0", "CC": "CHÉPICA", "LOC_URBANA": "CHÉPICA", "ESTACIONAL": "NOVIEMBRE", "USO_TUR": "ACTUAL", "DEMANDA": "LOCAL", "SERVICIOS": "AGUA POTABLE, ELECTRICIDAD", "COD_REG": 6, "COD_PROV": 63, "COD_COM": 6302, "DESCRIPCIO": "La Fiesta Costumbrista de la Esquila Chépica, que es organizada por la Asociación de Pequeños Ganaderos de Chépica y el municipio, busca no sólo entretener y dar una jornada de encuentro familiar, sino generar una oferta atractiva de productos.", "ESTADO_1": "BUENA", "POINT_X": -71.273836407000005, "POINT_Y": -34.728773714900001 }, "geometry": { "type": "Point", "coordinates": [ -71.273836406999976, -34.728773714883715, 0.0 ] } },
{ "type": "Feature", "properties": { "CODATRAC": "R060164", "JERARQUIA": "LOCAL", "CATEGORIA": "ACONTECIMIENTOS PROGRAMADOS", "TIPO": "EVENTOS MISCELÁNEOS", "SUBTIPO": "CARNAVAL O FIESTA COSTUMBRISTA", "NOMBRE": "FIESTA DE LA VENDIMIA Y DEL MELÓN CON VINO", "REGION": "REGIÓN DEL LIBERTADOR BERNARDO O'HIGGINS", "PROVINCIA": "COLCHAGUA", "COMUNA": "CHÉPICA", "LOCALIDAD": "CHÉPICA", "DIRECCION": "PLAZA DE ARMAS DE CHÉPICA", "TELEFONO": "(72) 2817216", "PROPIEDAD": "PRIVADA", "ADMINISTRA": "PRIVADA", "DISTCR": "76", "CR": "RANCAGUA", "DISTCC": "0", "CC": "CHÉPICA", "LOC_URBANA": "CHÉPICA", "ESTACIONAL": "ABRIL", "USO_TUR": "ACTUAL", "DEMANDA": "LOCAL", "SERVICIOS": "AGUA POTABLE, ELECTRICIDAD", "COD_REG": 6, "COD_PROV": 63, "COD_COM": 6302, "DESCRIPCIO": "Actividad Tradicional, artesanía y  gastronomía.", "ESTADO_1": "BUENA", "POINT_X": -71.273811123000002, "POINT_Y": -34.728647972899999 }, "geometry": { "type": "Point", "coordinates": [ -71.273811122999973, -34.728647972883749, 0.0 ] } },
{ "type": "Feature", "properties": { "CODATRAC": "R060288", "JERARQUIA": "LOCAL", "CATEGORIA": "REALIZACIONES TÉCNICAS Y CIENTÍFICAS CONTEMPORÁNEAS Y CULTURALES HISTÓRICAS", "TIPO": "OBRAS DE ARTE Y TÉCNICA", "SUBTIPO": "ARQUITECTURA", "NOMBRE": "PARROQUIA NUESTRA SEÑORA DEL CARMEN DE AUQUINCO", "REGION": "REGIÓN DEL LIBERTADOR BERNARDO O'HIGGINS", "PROVINCIA": "COLCHAGUA", "COMUNA": "CHÉPICA", "LOCALIDAD": "AUQUINCO", "DIRECCION": "A 27 KM AL SUR DE CHÉPICA", "TELEFONO": "(72) 2924063", "PROPIEDAD": "PRIVADA", "ADMINISTRA": "PRIVADA", "DISTCR": "0", "CR": "RANCAGUA", "DISTCC": "0", "CC": "RANCAGUA", "LOC_URBANA": "RANCAGUA", "ESTACIONAL": "TODO EL AÑO", "USO_TUR": "ACTUAL", "DEMANDA": "LOCAL, REGIONAL", "SERVICIOS": "SERVICIOS COMPLETOS", "COD_REG": 6, "COD_PROV": 63, "COD_COM": 6302, "DESCRIPCIO": "El terreno de una cuadra para construir una parroquia y la casa parroquial fue donado en 1897 por don Alberto Izquierdo. A fines de los 40 el maestro Miguel Soto levanta el actual templo, el que tiene capacidad para 120 personas sentadas.", "ESTADO_1": "BUENA", "POINT_X": -71.197691942000006, "POINT_Y": -34.761735125900003 }, "geometry": { "type": "Point", "coordinates": [ -71.197691941999949, -34.761735125884144, 0.0 ] } },
{ "type": "Feature", "properties": { "CODATRAC": "R060330", "JERARQUIA": "LOCAL", "CATEGORIA": "FOLKLORE", "TIPO": "ARQUITECTURA POPULAR ESPONTÁNEA", "SUBTIPO": "PUEBLO O ALDEA TRADICIONAL", "NOMBRE": "RINCONADA DE MENESES", "REGION": "REGIÓN DEL LIBERTADOR BERNARDO O'HIGGINS", "PROVINCIA": "COLCHAGUA", "COMUNA": "CHÉPICA", "LOCALIDAD": "RINCONADA DE MENESES", "DIRECCION": "A 8 KM DE CHÉPICA", "TELEFONO": "(72) 2817213", "PROPIEDAD": "PÚBLICA", "ADMINISTRA": "PÚBLICA", "DISTCR": "75", "CR": "RANCAGUA", "DISTCC": "0", "CC": "LAS CABRAS", "LOC_URBANA": "LAS CABRAS", "ESTACIONAL": "OCTUBRE", "USO_TUR": "ACTUAL", "DEMANDA": "LOCAL, REGIONAL", "SERVICIOS": "SERVICIOS COMPLETOS", "COD_REG": 6, "COD_PROV": 63, "COD_COM": 6302, "DESCRIPCIO": "Localidad rural enclavada en una rinconada de los cerros de la cordillera de la costa, se destaca la crianza y venta de cordero, los que son trasladados a la Cordillera de Los Andes de la Región del Maule.", "ESTADO_1": "BUENA", "POINT_X": -71.265392965999993, "POINT_Y": -34.783050060900003 }, "geometry": { "type": "Point", "coordinates": [ -71.265392965999979, -34.783050060884335, 0.0 ] } },
{ "type": "Feature", "properties": { "CODATRAC": "R060331", "JERARQUIA": "LOCAL", "CATEGORIA": "FOLKLORE", "TIPO": "ARQUITECTURA POPULAR ESPONTÁNEA", "SUBTIPO": "PUEBLO O ALDEA TRADICIONAL", "NOMBRE": "RINCONADA DE NAVARRO", "REGION": "REGIÓN DEL LIBERTADOR BERNARDO O'HIGGINS", "PROVINCIA": "COLCHAGUA", "COMUNA": "CHÉPICA", "LOCALIDAD": "RINCONADA DE NAVARRO", "DIRECCION": "A 25 KM AL SUR DE CHÉPICA", "TELEFONO": "(72) 2817213", "PROPIEDAD": "PÚBLICA", "ADMINISTRA": "PÚBLICA-PRIVADA", "DISTCR": "75", "CR": "RANCAGUA", "DISTCC": "0", "CC": "LAS CABRAS", "LOC_URBANA": "LAS CABRAS", "ESTACIONAL": "FEBRERO", "USO_TUR": "ACTUAL", "DEMANDA": "LOCAL, REGIONAL", "SERVICIOS": "SERVICIOS COMPLETOS", "COD_REG": 6, "COD_PROV": 63, "COD_COM": 6302, "DESCRIPCIO": "Siguiendo por la ruta I-86 hacía Auquinco, es necesario desviarse hacia la ruta I-30-J por la cual se accede a rinconada de Navarro, en el camino, típico del campo Chileno, se pueden observar la arquitectura tradicional con la que construían sus casas", "ESTADO_1": "BUENA", "POINT_X": -71.218901332000002, "POINT_Y": -34.806511559900002 }, "geometry": { "type": "Point", "coordinates": [ -71.218901331999973, -34.806511559884619, 0.0 ] } }
]
}
