{
"type": "FeatureCollection",
"crs": { "type": "name", "properties": { "name": "urn:ogc:def:crs:EPSG::4979" } },
"features": [
{ "type": "Feature", "properties": { "CODATRAC": "R080029", "JERARQUIA": "LOCAL", "CATEGORIA": "FOLKLORE", "TIPO": "ARTESANÍA TRADICIONAL", "SUBTIPO": "FIBRA VEGETAL O CESTERÍA", "NOMBRE": "CESTERÍA DE HUALQUI", "REGION": "REGIÓN DEL BIOBÍO", "PROVINCIA": "CONCEPCIÓN", "COMUNA": "HUALQUI", "LOCALIDAD": "HUALQUI", "DIRECCION": "", "TELEFONO": "(41) 2780671", "PROPIEDAD": "PRIVADA", "ADMINISTRA": "PRIVADA", "DISTCR": "24", "CR": "CONCEPCIÓN", "DISTCC": "0", "CC": "HUALQUI", "LOC_URBANA": "HUALQUI", "ESTACIONAL": "TODO EL AÑO", "USO_TUR": "ACTUAL", "DEMANDA": "LOCAL", "SERVICIOS": "AGUA POTABLE, ELECTRICIDAD", "COD_REG": 8, "COD_PROV": 81, "COD_COM": 8105, "DESCRIPCIO": "Tiene origen indígena y destaca por la complejidad y belleza de su trama, el material es el chupón y coirón con el cual van formando un cordón firme, apretado y largo. El coirón forma el alma del tejido y el chupón se embarrila en torno a éste.", "ESTADO_1": "BUENA", "POINT_X": -72.937936713300004, "POINT_Y": -36.976461700199998 }, "geometry": { "type": "Point", "coordinates": [ -72.937936713308545, -36.976461700247114, 0.0 ] } },
{ "type": "Feature", "properties": { "CODATRAC": "R080053", "JERARQUIA": "LOCAL", "CATEGORIA": "ACONTECIMIENTOS PROGRAMADOS", "TIPO": "EVENTOS MISCELÁNEOS", "SUBTIPO": "CARNAVAL O FIESTA COSTUMBRISTA", "NOMBRE": "FIESTA DEL CHOCLO EN HUALQUI", "REGION": "REGIÓN DEL BIOBÍO", "PROVINCIA": "CONCEPCIÓN", "COMUNA": "HUALQUI", "LOCALIDAD": "HUALQUI", "DIRECCION": "", "TELEFONO": "", "PROPIEDAD": "", "ADMINISTRA": "", "DISTCR": "0", "CR": "", "DISTCC": "0", "CC": "", "LOC_URBANA": "", "ESTACIONAL": "", "USO_TUR": "", "DEMANDA": "", "SERVICIOS": "", "COD_REG": 8, "COD_PROV": 81, "COD_COM": 8105, "DESCRIPCIO": "Comienza con el Campeonato Nacional de Cueca Padre e Hijo, un Festival de la Voz y la presentación de varios músicos locales y nacionales. Son en total 12 días llenos de actividades donde se destaca la Feria Costumbrista.", "ESTADO_1": "", "POINT_X": -72.938389946399994, "POINT_Y": -36.975918921599998 }, "geometry": { "type": "Point", "coordinates": [ -72.938389946438747, -36.975918921620803, 0.0 ] } },
{ "type": "Feature", "properties": { "CODATRAC": "R080064", "JERARQUIA": "LOCAL", "CATEGORIA": "FOLKLORE", "TIPO": "ARQUITECTURA POPULAR ESPONTÁNEA", "SUBTIPO": "PUEBLO O ALDEA TRADICIONAL", "NOMBRE": "HUALQUI", "REGION": "REGIÓN DEL BIOBÍO", "PROVINCIA": "CONCEPCIÓN", "COMUNA": "HUALQUI", "LOCALIDAD": "HUALQUI", "DIRECCION": "A 13 KM AL SUR DE CHIGUAYANTE", "TELEFONO": "(41) 2780671", "PROPIEDAD": "PÚBLICA", "ADMINISTRA": "PÚBLICA", "DISTCR": "24", "CR": "CONCEPCIÓN", "DISTCC": "0", "CC": "HUALQUI", "LOC_URBANA": "HUALQUI", "ESTACIONAL": "TODO EL AÑO", "USO_TUR": "ACTUAL", "DEMANDA": "LOCAL", "SERVICIOS": "AGUA POTABLE, ELECTRICIDAD", "COD_REG": 8, "COD_PROV": 81, "COD_COM": 8105, "DESCRIPCIO": "Hualqui fue fundada el 24 de octubre de 1757 por el Gobernador del reino de Chile don Manuel de Amat y Junient, ingresando a las páginas de la Historia con los Lavaderos de Oro de Pedro de Valdivia en Quilacoya.", "ESTADO_1": "BUENA", "POINT_X": -72.938451068000006, "POINT_Y": -36.975985175600002 }, "geometry": { "type": "Point", "coordinates": [ -72.938451067962262, -36.975985175575261, 0.0 ] } }
]
}
