{
"type": "FeatureCollection",
"crs": { "type": "name", "properties": { "name": "urn:ogc:def:crs:OGC:1.3:CRS84" } },
"features": [
{ "type": "Feature", "properties": { "arclim_id": "8310", "NOM_COMUNA": "SAN ROSENDO", "NOM_PROVIN": "BIOBÍO", "NOM_REGION": "REGIÓN DEL BIOBÍO" }, "geometry": { "type": "Polygon", "coordinates": [ [ [ -72.64266, -37.23722 ], [ -72.68762, -37.253 ], [ -72.70753, -37.25394 ], [ -72.72823, -37.27084 ], [ -72.74053, -37.25836 ], [ -72.74201, -37.23802 ], [ -72.77264, -37.20505 ], [ -72.80857, -37.20897 ], [ -72.82294, -37.19876 ], [ -72.81271, -37.17294 ], [ -72.79449, -37.16573 ], [ -72.77872, -37.16779 ], [ -72.76795, -37.19077 ], [ -72.75277, -37.19476 ], [ -72.74032, -37.18384 ], [ -72.67848, -37.18773 ], [ -72.67832, -37.17408 ], [ -72.66145, -37.18435 ], [ -72.63428, -37.21797 ], [ -72.64266, -37.23722 ] ] ] } }
]
}
